{
  "metadata": {
    "file_name": "2000_아무도 기다리지 않았다_공선옥_tagged.txt",
    "author": "공선옥",
    "title": "아무도 기다리지 않았다",
    "year": "2000"
  },
  "sentence_metrics": {
    "sentence_count": 470,
    "sentence_char_lengths": [
      10,
      14,
      5,
      31,
      40,
      25,
      30,
      26,
      19,
      22,
      20,
      21,
      66,
      50,
      46,
      17,
      32,
      17,
      16,
      14,
      116,
      94,
      11,
      21,
      18,
      50,
      53,
      67,
      52,
      51,
      39,
      61,
      21,
      27,
      29,
      23,
      31,
      21,
      6,
      10,
      52,
      53,
      15,
      14,
      20,
      20,
      12,
      27,
      29,
      34,
      26,
      44,
      48,
      69,
      36,
      37,
      30,
      31,
      11,
      9,
      8,
      7,
      5,
      1,
      11,
      2,
      5,
      8,
      8,
      7,
      5,
      3,
      33,
      50,
      17,
      98,
      24,
      36,
      33,
      47,
      46,
      40,
      10,
      37,
      17,
      7,
      28,
      13,
      6,
      16,
      6,
      3,
      3,
      5,
      67,
      23,
      19,
      9,
      8,
      14,
      12,
      20,
      23,
      13,
      12,
      7,
      6,
      4,
      5,
      24,
      20,
      9,
      100,
      10,
      4,
      18,
      37,
      15,
      14,
      38,
      3,
      12,
      8,
      9,
      8,
      14,
      7,
      19,
      26,
      50,
      44,
      30,
      7,
      29,
      22,
      17,
      9,
      54,
      4,
      15,
      17,
      24,
      31,
      15,
      43,
      34,
      84,
      42,
      82,
      76,
      7,
      22,
      15,
      27,
      61,
      9,
      26,
      24,
      49,
      14,
      23,
      51,
      10,
      29,
      20,
      20,
      12,
      21,
      6,
      1,
      13,
      14,
      13,
      7,
      4,
      19,
      7,
      4,
      25,
      21,
      11,
      31,
      19,
      23,
      8,
      13,
      9,
      9,
      45,
      19,
      73,
      24,
      8,
      38,
      5,
      21,
      26,
      13,
      11,
      27,
      27,
      11,
      11,
      30,
      63,
      28,
      6,
      34,
      19,
      13,
      44,
      15,
      12,
      14,
      17,
      11,
      25,
      10,
      6,
      6,
      4,
      10,
      25,
      8,
      18,
      10,
      37,
      24,
      11,
      7,
      17,
      4,
      11,
      6,
      10,
      12,
      9,
      14,
      37,
      23,
      17,
      11,
      11,
      15,
      11,
      12,
      5,
      12,
      8,
      123,
      16,
      9,
      14,
      19,
      1,
      2,
      13,
      25,
      14,
      24,
      15,
      17,
      28,
      25,
      69,
      67,
      46,
      36,
      81,
      41,
      60,
      49,
      18,
      78,
      6,
      30,
      33,
      65,
      15,
      46,
      19,
      22,
      5,
      37,
      25,
      20,
      17,
      21,
      6,
      24,
      7,
      12,
      7,
      37,
      14,
      15,
      15,
      12,
      13,
      21,
      42,
      29,
      10,
      8,
      9,
      37,
      29,
      55,
      21,
      29,
      11,
      12,
      92,
      9,
      62,
      20,
      22,
      29,
      34,
      62,
      19,
      75,
      21,
      17,
      12,
      10,
      13,
      4,
      26,
      8,
      7,
      14,
      43,
      7,
      10,
      19,
      5,
      21,
      13,
      16,
      15,
      46,
      16,
      14,
      13,
      15,
      26,
      34,
      27,
      31,
      15,
      18,
      23,
      11,
      30,
      15,
      44,
      14,
      35,
      18,
      44,
      12,
      26,
      27,
      9,
      14,
      41,
      37,
      14,
      8,
      21,
      15,
      24,
      42,
      6,
      24,
      16,
      17,
      5,
      10,
      14,
      8,
      12,
      7,
      4,
      5,
      21,
      23,
      14,
      11,
      68,
      5,
      12,
      6,
      9,
      2,
      15,
      8,
      21,
      9,
      18,
      28,
      8,
      27,
      44,
      5,
      20,
      5,
      11,
      7,
      13,
      10,
      43,
      11,
      9,
      4,
      28,
      11,
      15,
      31,
      22,
      5,
      9,
      16,
      11,
      17,
      12,
      15,
      11,
      48,
      4,
      16,
      55,
      23,
      12,
      66,
      13,
      11,
      13,
      22,
      26,
      18,
      14,
      27,
      15,
      18,
      36,
      12,
      14,
      7,
      26,
      15,
      14,
      23,
      7,
      14,
      11,
      1,
      7,
      14,
      38,
      16,
      50,
      29,
      34,
      17,
      5,
      12,
      21,
      17
    ],
    "sentence_word_lengths": [
      3,
      7,
      1,
      11,
      11,
      8,
      11,
      9,
      7,
      7,
      6,
      8,
      23,
      12,
      16,
      5,
      10,
      5,
      4,
      6,
      39,
      35,
      3,
      6,
      6,
      15,
      19,
      25,
      20,
      15,
      13,
      21,
      7,
      10,
      8,
      7,
      12,
      6,
      2,
      4,
      18,
      18,
      6,
      4,
      8,
      7,
      5,
      9,
      10,
      11,
      10,
      18,
      17,
      24,
      12,
      12,
      9,
      9,
      5,
      2,
      3,
      3,
      2,
      1,
      3,
      1,
      2,
      3,
      3,
      2,
      1,
      1,
      11,
      13,
      6,
      38,
      7,
      11,
      12,
      17,
      14,
      17,
      5,
      13,
      6,
      2,
      9,
      4,
      2,
      4,
      2,
      2,
      1,
      2,
      24,
      10,
      7,
      5,
      3,
      7,
      4,
      7,
      11,
      4,
      4,
      4,
      2,
      1,
      2,
      8,
      7,
      2,
      36,
      4,
      2,
      8,
      11,
      6,
      4,
      13,
      2,
      4,
      4,
      4,
      3,
      5,
      2,
      6,
      10,
      19,
      15,
      9,
      3,
      11,
      8,
      7,
      3,
      16,
      1,
      5,
      5,
      8,
      10,
      6,
      14,
      12,
      29,
      14,
      25,
      28,
      2,
      7,
      6,
      8,
      19,
      5,
      9,
      8,
      15,
      3,
      9,
      16,
      3,
      13,
      7,
      6,
      5,
      7,
      2,
      1,
      4,
      4,
      4,
      2,
      1,
      9,
      2,
      1,
      8,
      7,
      3,
      13,
      8,
      9,
      2,
      4,
      4,
      4,
      17,
      6,
      24,
      7,
      3,
      12,
      3,
      8,
      9,
      3,
      4,
      9,
      11,
      5,
      4,
      10,
      21,
      11,
      2,
      15,
      5,
      4,
      15,
      4,
      6,
      6,
      7,
      4,
      10,
      4,
      2,
      2,
      2,
      3,
      9,
      4,
      8,
      5,
      15,
      8,
      4,
      2,
      4,
      1,
      3,
      2,
      4,
      5,
      4,
      5,
      11,
      9,
      3,
      3,
      4,
      5,
      4,
      3,
      1,
      4,
      3,
      41,
      7,
      3,
      4,
      6,
      1,
      1,
      5,
      8,
      5,
      7,
      6,
      5,
      10,
      9,
      27,
      20,
      17,
      12,
      26,
      15,
      22,
      17,
      6,
      26,
      2,
      11,
      11,
      23,
      5,
      16,
      6,
      8,
      2,
      12,
      9,
      7,
      5,
      8,
      3,
      10,
      2,
      5,
      2,
      11,
      5,
      5,
      6,
      5,
      4,
      7,
      15,
      11,
      5,
      5,
      3,
      15,
      10,
      18,
      8,
      10,
      3,
      3,
      35,
      3,
      20,
      8,
      9,
      7,
      10,
      22,
      8,
      23,
      7,
      8,
      4,
      5,
      4,
      1,
      10,
      3,
      3,
      5,
      17,
      3,
      4,
      6,
      2,
      9,
      5,
      6,
      6,
      18,
      7,
      7,
      4,
      6,
      10,
      11,
      10,
      10,
      6,
      8,
      9,
      4,
      14,
      3,
      13,
      5,
      11,
      5,
      14,
      4,
      11,
      10,
      2,
      4,
      14,
      13,
      5,
      2,
      6,
      7,
      8,
      14,
      2,
      8,
      6,
      7,
      2,
      4,
      5,
      3,
      4,
      3,
      1,
      1,
      8,
      8,
      4,
      4,
      24,
      2,
      6,
      3,
      4,
      1,
      4,
      3,
      6,
      3,
      7,
      8,
      3,
      11,
      12,
      3,
      9,
      2,
      5,
      4,
      5,
      4,
      12,
      5,
      3,
      1,
      11,
      4,
      5,
      12,
      8,
      3,
      2,
      6,
      5,
      5,
      6,
      6,
      3,
      15,
      1,
      5,
      16,
      8,
      4,
      24,
      6,
      3,
      5,
      7,
      10,
      6,
      4,
      9,
      4,
      6,
      10,
      5,
      4,
      2,
      9,
      6,
      5,
      8,
      4,
      5,
      3,
      1,
      2,
      6,
      14,
      5,
      17,
      8,
      15,
      6,
      2,
      4,
      7,
      5
    ],
    "sentence_morpheme_lengths": [
      9,
      12,
      5,
      24,
      31,
      18,
      26,
      23,
      15,
      15,
      16,
      18,
      49,
      34,
      30,
      13,
      18,
      13,
      13,
      12,
      85,
      77,
      10,
      16,
      16,
      37,
      40,
      52,
      40,
      36,
      32,
      49,
      16,
      18,
      22,
      15,
      23,
      13,
      5,
      8,
      41,
      42,
      12,
      9,
      14,
      13,
      10,
      18,
      25,
      28,
      22,
      34,
      36,
      52,
      32,
      24,
      23,
      20,
      8,
      6,
      8,
      10,
      7,
      4,
      9,
      4,
      7,
      10,
      9,
      7,
      7,
      5,
      23,
      27,
      12,
      76,
      23,
      24,
      27,
      37,
      32,
      34,
      9,
      28,
      15,
      7,
      23,
      9,
      29,
      5,
      4,
      6,
      47,
      18,
      14,
      10,
      7,
      13,
      11,
      37,
      10,
      9,
      10,
      8,
      6,
      6,
      17,
      14,
      101,
      6,
      21,
      25,
      13,
      13,
      37,
      8,
      8,
      9,
      10,
      12,
      6,
      12,
      18,
      98,
      7,
      24,
      18,
      15,
      7,
      38,
      2,
      12,
      13,
      20,
      21,
      12,
      35,
      27,
      59,
      36,
      70,
      66,
      5,
      17,
      17,
      19,
      45,
      11,
      21,
      18,
      31,
      10,
      18,
      42,
      8,
      25,
      15,
      16,
      14,
      19,
      5,
      2,
      10,
      11,
      15,
      6,
      5,
      18,
      7,
      5,
      16,
      15,
      10,
      25,
      15,
      22,
      8,
      11,
      10,
      10,
      34,
      15,
      52,
      14,
      8,
      30,
      9,
      14,
      20,
      11,
      10,
      22,
      21,
      10,
      10,
      22,
      48,
      23,
      7,
      30,
      17,
      10,
      34,
      9,
      17,
      12,
      19,
      10,
      22,
      13,
      8,
      7,
      6,
      8,
      19,
      11,
      15,
      10,
      31,
      17,
      15,
      11,
      5,
      13,
      8,
      11,
      12,
      11,
      12,
      28,
      19,
      12,
      8,
      9,
      11,
      9,
      11,
      5,
      9,
      7,
      99,
      12,
      11,
      9,
      14,
      4,
      4,
      11,
      18,
      9,
      19,
      12,
      13,
      23,
      19,
      56,
      52,
      36,
      31,
      63,
      31,
      42,
      37,
      14,
      57,
      6,
      21,
      26,
      50,
      12,
      36,
      12,
      17,
      6,
      27,
      17,
      15,
      10,
      19,
      9,
      19,
      5,
      13,
      8,
      26,
      11,
      11,
      14,
      10,
      11,
      17,
      31,
      31,
      10,
      8,
      13,
      30,
      22,
      38,
      17,
      25,
      11,
      10,
      65,
      8,
      46,
      18,
      19,
      19,
      29,
      51,
      16,
      60,
      17,
      15,
      14,
      8,
      11,
      4,
      23,
      9,
      8,
      10,
      38,
      7,
      9,
      16,
      6,
      16,
      10,
      15,
      14,
      34,
      15,
      14,
      11,
      14,
      22,
      31,
      21,
      27,
      12,
      13,
      18,
      14,
      26,
      12,
      34,
      10,
      24,
      14,
      31,
      10,
      24,
      23,
      7,
      10,
      30,
      31,
      10,
      5,
      15,
      12,
      19,
      30,
      8,
      20,
      17,
      15,
      7,
      10,
      33,
      7,
      5,
      5,
      17,
      18,
      13,
      10,
      51,
      5,
      12,
      10,
      10,
      5,
      11,
      11,
      17,
      8,
      14,
      22,
      7,
      22,
      32,
      7,
      19,
      4,
      11,
      9,
      10,
      8,
      27,
      11,
      8,
      6,
      24,
      10,
      11,
      25,
      17,
      8,
      5,
      15,
      10,
      27,
      12,
      54,
      12,
      40,
      21,
      7,
      55,
      12,
      9,
      11,
      17,
      19,
      14,
      8,
      18,
      8,
      14,
      25,
      11,
      10,
      6,
      20,
      13,
      12,
      17,
      12,
      11,
      9,
      3,
      7,
      12,
      27,
      12,
      36,
      22,
      29,
      14,
      9,
      10,
      17,
      11
    ],
    "word_char_lengths": [
      3,
      4,
      3,
      2,
      2,
      2,
      2,
      1,
      2,
      3,
      5,
      5,
      1,
      2,
      2,
      4,
      1,
      3,
      2,
      5,
      3,
      3,
      3,
      5,
      3,
      2,
      6,
      8,
      2,
      5,
      1,
      2,
      3,
      3,
      3,
      6,
      2,
      2,
      1,
      2,
      6,
      4,
      3,
      1,
      3,
      2,
      3,
      3,
      2,
      3,
      3,
      3,
      2,
      3,
      3,
      3,
      3,
      2,
      2,
      3,
      5,
      3,
      4,
      2,
      1,
      3,
      3,
      3,
      3,
      3,
      6,
      2,
      3,
      2,
      3,
      3,
      4,
      3,
      4,
      4,
      2,
      3,
      1,
      4,
      3,
      4,
      2,
      1,
      3,
      5,
      3,
      3,
      3,
      3,
      4,
      2,
      3,
      3,
      2,
      5,
      2,
      1,
      3,
      1,
      1,
      1,
      1,
      5,
      3,
      4,
      5,
      3,
      3,
      6,
      4,
      4,
      4,
      4,
      4,
      5,
      6,
      4,
      3,
      3,
      4,
      3,
      4,
      3,
      2,
      2,
      1,
      3,
      2,
      3,
      4,
      3,
      2,
      4,
      3,
      3,
      2,
      3,
      6,
      3,
      3,
      4,
      2,
      3,
      4,
      4,
      3,
      4,
      3,
      2,
      3,
      3,
      3,
      3,
      3,
      5,
      4,
      3,
      6,
      3,
      4,
      2,
      1,
      2,
      2,
      3,
      3,
      2,
      1,
      2,
      1,
      4,
      4,
      2,
      4,
      3,
      4,
      4,
      2,
      3,
      1,
      3,
      1,
      4,
      4,
      3,
      3,
      3,
      3,
      3,
      4,
      5,
      1,
      4,
      2,
      3,
      2,
      4,
      3,
      3,
      4,
      3,
      3,
      4,
      4,
      2,
      2,
      5,
      3,
      4,
      2,
      3,
      2,
      3,
      5,
      3,
      4,
      3,
      2,
      2,
      2,
      1,
      1,
      2,
      2,
      2,
      2,
      3,
      3,
      1,
      2,
      3,
      5,
      3,
      3,
      3,
      2,
      3,
      3,
      3,
      5,
      1,
      5,
      4,
      4,
      2,
      6,
      3,
      2,
      6,
      2,
      1,
      2,
      5,
      2,
      3,
      3,
      3,
      2,
      2,
      3,
      3,
      5,
      4,
      3,
      5,
      2,
      4,
      4,
      4,
      4,
      3,
      3,
      1,
      3,
      2,
      3,
      5,
      1,
      2,
      3,
      2,
      4,
      3,
      3,
      2,
      4,
      2,
      3,
      3,
      2,
      3,
      1,
      4,
      6,
      3,
      2,
      3,
      2,
      4,
      3,
      2,
      1,
      3,
      3,
      1,
      3,
      2,
      2,
      1,
      3,
      2,
      3,
      5,
      3,
      2,
      2,
      2,
      3,
      2,
      1,
      2,
      2,
      5,
      3,
      2,
      3,
      3,
      2,
      2,
      3,
      3,
      3,
      4,
      3,
      4,
      3,
      2,
      5,
      2,
      3,
      6,
      4,
      4,
      1,
      5,
      3,
      4,
      2,
      3,
      3,
      3,
      4,
      3,
      2,
      3,
      1,
      2,
      3,
      3,
      5,
      4,
      2,
      4,
      4,
      4,
      3,
      6,
      5,
      3,
      2,
      3,
      2,
      1,
      4,
      1,
      3,
      2,
      2,
      3,
      2,
      2,
      3,
      2,
      4,
      3,
      3,
      3,
      4,
      2,
      1,
      1,
      4,
      2,
      2,
      6,
      5,
      2,
      2,
      2,
      3,
      4,
      5,
      4,
      4,
      3,
      3,
      3,
      3,
      1,
      3,
      4,
      5,
      3,
      4,
      2,
      2,
      2,
      4,
      3,
      2,
      1,
      3,
      3,
      2,
      3,
      4,
      2,
      3,
      6,
      5,
      3,
      2,
      3,
      3,
      2,
      3,
      2,
      3,
      4,
      3,
      2,
      4,
      3,
      3,
      3,
      3,
      3,
      3,
      3,
      2,
      1,
      3,
      5,
      2,
      2,
      3,
      1,
      3,
      4,
      2,
      4,
      2,
      4,
      3,
      3,
      2,
      3,
      2,
      2,
      4,
      3,
      4,
      4,
      3,
      4,
      2,
      3,
      1,
      3,
      2,
      4,
      4,
      4,
      2,
      2,
      3,
      2,
      4,
      3,
      1,
      2,
      3,
      2,
      4,
      5,
      3,
      2,
      2,
      2,
      2,
      2,
      2,
      3,
      3,
      3,
      2,
      3,
      2,
      5,
      3,
      4,
      1,
      4,
      3,
      2,
      3,
      4,
      2,
      4,
      3,
      3,
      1,
      4,
      2,
      3,
      4,
      3,
      3,
      2,
      1,
      3,
      5,
      3,
      5,
      3,
      2,
      3,
      2,
      2,
      2,
      4,
      2,
      2,
      4,
      1,
      2,
      2,
      2,
      1,
      4,
      2,
      2,
      4,
      2,
      3,
      3,
      2,
      3,
      2,
      2,
      3,
      4,
      4,
      1,
      5,
      4,
      2,
      1,
      1,
      4,
      4,
      3,
      2,
      2,
      3,
      3,
      3,
      3,
      3,
      3,
      2,
      3,
      4,
      3,
      3,
      4,
      3,
      1,
      2,
      3,
      2,
      4,
      2,
      4,
      2,
      3,
      2,
      3,
      2,
      5,
      4,
      3,
      2,
      5,
      4,
      2,
      2,
      3,
      4,
      3,
      3,
      3,
      2,
      2,
      3,
      4,
      2,
      4,
      2,
      3,
      2,
      4,
      3,
      4,
      2,
      4,
      3,
      4,
      4,
      1,
      4,
      4,
      4,
      3,
      1,
      5,
      4,
      4,
      3,
      4,
      3,
      3,
      2,
      4,
      4,
      2,
      2,
      1,
      3,
      3,
      6,
      3,
      3,
      2,
      3,
      2,
      2,
      3,
      2,
      3,
      1,
      3,
      4,
      4,
      2,
      2,
      3,
      3,
      2,
      3,
      3,
      2,
      3,
      3,
      4,
      5,
      3,
      2,
      2,
      1,
      4,
      5,
      5,
      2,
      3,
      2,
      3,
      4,
      4,
      3,
      5,
      2,
      2,
      3,
      5,
      3,
      4,
      6,
      3,
      6,
      4,
      3,
      3,
      5,
      2,
      2,
      2,
      4,
      2,
      4,
      3,
      5,
      3,
      2,
      3,
      2,
      1,
      2,
      2,
      3,
      2,
      2,
      1,
      3,
      3,
      5,
      3,
      5,
      2,
      4,
      3,
      2,
      3,
      2,
      2,
      2,
      2,
      1,
      3,
      2,
      2,
      2,
      3,
      1,
      2,
      3,
      3,
      5,
      3,
      3,
      5,
      2,
      2,
      3,
      3,
      2,
      5,
      3,
      3,
      5,
      2,
      5,
      3,
      2,
      2,
      2,
      5,
      2,
      4,
      3,
      3,
      2,
      3,
      3,
      2,
      4,
      2,
      2,
      1,
      3,
      2,
      3,
      5,
      3,
      3,
      1,
      3,
      4,
      2,
      3,
      2,
      4,
      2,
      2,
      5,
      1,
      5,
      5,
      2,
      4,
      2,
      3,
      3,
      4,
      2,
      6,
      1,
      2,
      3,
      2,
      5,
      2,
      1,
      2,
      2,
      3,
      4,
      2,
      2,
      2,
      1,
      4,
      2,
      3,
      2,
      1,
      2,
      2,
      3,
      2,
      1,
      4,
      4,
      2,
      4,
      3,
      2,
      3,
      3,
      2,
      4,
      4,
      2,
      3,
      3,
      4,
      1,
      2,
      5,
      3,
      2,
      3,
      3,
      6,
      2,
      3,
      2,
      4,
      6,
      2,
      3,
      2,
      2,
      4,
      4,
      5,
      2,
      5,
      3,
      3,
      2,
      1,
      3,
      2,
      3,
      4,
      1,
      2,
      1,
      4,
      2,
      2,
      2,
      2,
      2,
      4,
      4,
      4,
      3,
      3,
      3,
      4,
      3,
      1,
      1,
      2,
      5,
      4,
      4,
      3,
      1,
      3,
      2,
      3,
      2,
      2,
      2,
      3,
      2,
      3,
      4,
      2,
      2,
      3,
      3,
      2,
      2,
      1,
      2,
      2,
      2,
      3,
      1,
      4,
      3,
      1,
      2,
      3,
      2,
      1,
      2,
      3,
      6,
      1,
      2,
      5,
      4,
      2,
      2,
      3,
      1,
      3,
      1,
      3,
      1,
      3,
      2,
      4,
      2,
      1,
      2,
      2,
      2,
      3,
      4,
      3,
      3,
      3,
      4,
      3,
      2,
      2,
      2,
      1,
      2,
      2,
      4,
      4,
      2,
      3,
      3,
      2,
      3,
      2,
      4,
      5,
      1,
      4,
      3,
      4,
      3,
      3,
      2,
      2,
      3,
      4,
      5,
      4,
      2,
      3,
      2,
      4,
      3,
      2,
      2,
      2,
      3,
      3,
      3,
      4,
      4,
      3,
      3,
      2,
      3,
      3,
      4,
      2,
      4,
      2,
      2,
      4,
      4,
      2,
      2,
      2,
      4,
      1,
      1,
      1,
      2,
      6,
      2,
      4,
      2,
      1,
      3,
      2,
      2,
      3,
      4,
      2,
      3,
      2,
      1,
      1,
      2,
      3,
      4,
      3,
      2,
      3,
      5,
      4,
      3,
      3,
      2,
      5,
      2,
      4,
      2,
      3,
      3,
      1,
      3,
      5,
      2,
      4,
      2,
      2,
      2,
      2,
      2,
      3,
      4,
      5,
      4,
      4,
      3,
      1,
      4,
      2,
      1,
      2,
      4,
      1,
      5,
      2,
      1,
      3,
      2,
      3,
      3,
      1,
      2,
      1,
      3,
      4,
      1,
      2,
      3,
      5,
      3,
      3,
      4,
      3,
      2,
      5,
      4,
      2,
      3,
      2,
      3,
      3,
      3,
      2,
      1,
      3,
      2,
      4,
      3,
      4,
      2,
      2,
      2,
      3,
      2,
      3,
      4,
      2,
      2,
      3,
      2,
      2,
      3,
      2,
      3,
      3,
      2,
      4,
      1,
      3,
      4,
      4,
      2,
      2,
      2,
      6,
      3,
      2,
      1,
      3,
      4,
      5,
      2,
      2,
      3,
      5,
      2,
      5,
      1,
      4,
      4,
      4,
      2,
      2,
      3,
      2,
      3,
      4,
      2,
      3,
      3,
      1,
      3,
      1,
      5,
      2,
      3,
      3,
      3,
      2,
      1,
      4,
      3,
      3,
      3,
      2,
      2,
      2,
      4,
      2,
      2,
      2,
      2,
      5,
      2,
      2,
      4,
      3,
      2,
      5,
      4,
      4,
      3,
      3,
      1,
      2,
      4,
      4,
      5,
      6,
      4,
      4,
      3,
      3,
      3,
      2,
      3,
      3,
      3,
      5,
      3,
      4,
      3,
      2,
      1,
      4,
      3,
      5,
      2,
      3,
      5,
      4,
      4,
      2,
      2,
      2,
      3,
      2,
      4,
      1,
      2,
      3,
      2,
      3,
      4,
      3,
      3,
      2,
      3,
      3,
      4,
      4,
      6,
      2,
      5,
      1,
      3,
      1,
      3,
      4,
      2,
      3,
      2,
      3,
      2,
      2,
      5,
      1,
      1,
      5,
      4,
      3,
      3,
      2,
      2,
      2,
      3,
      2,
      3,
      7,
      4,
      2,
      2,
      5,
      2,
      2,
      3,
      4,
      2,
      3,
      3,
      2,
      3,
      2,
      2,
      3,
      1,
      4,
      3,
      5,
      1,
      3,
      4,
      2,
      2,
      3,
      6,
      3,
      3,
      2,
      4,
      3,
      3,
      3,
      3,
      2,
      3,
      4,
      6,
      4,
      3,
      3,
      3,
      3,
      2,
      2,
      3,
      4,
      2,
      2,
      3,
      3,
      2,
      4,
      3,
      6,
      5,
      3,
      4,
      1,
      2,
      3,
      2,
      2,
      3,
      3,
      1,
      3,
      3,
      2,
      3,
      3,
      3,
      2,
      3,
      3,
      2,
      2,
      3,
      3,
      3,
      2,
      6,
      3,
      3,
      3,
      4,
      4,
      3,
      3,
      4,
      5,
      3,
      2,
      3,
      2,
      2,
      1,
      3,
      2,
      3,
      4,
      6,
      5,
      3,
      3,
      2,
      3,
      2,
      3,
      3,
      4,
      4,
      3,
      5,
      2,
      4,
      3,
      3,
      3,
      1,
      2,
      4,
      3,
      4,
      4,
      3,
      4,
      2,
      2,
      2,
      1,
      1,
      3,
      4,
      3,
      3,
      2,
      4,
      2,
      3,
      3,
      2,
      3,
      3,
      1,
      4,
      3,
      3,
      5,
      2,
      2,
      2,
      5,
      4,
      1,
      3,
      6,
      3,
      3,
      2,
      3,
      3,
      3,
      6,
      3,
      7,
      5,
      2,
      2,
      1,
      2,
      2,
      3,
      3,
      4,
      1,
      5,
      7,
      2,
      3,
      3,
      7,
      2,
      4,
      2,
      4,
      1,
      4,
      3,
      2,
      2,
      2,
      3,
      4,
      3,
      3,
      2,
      3,
      1,
      1,
      2,
      1,
      2,
      3,
      3,
      2,
      3,
      3,
      3,
      2,
      2,
      1,
      5,
      3,
      1,
      6,
      1,
      2,
      5,
      3,
      3,
      6,
      2,
      1,
      2,
      4,
      3,
      2,
      1,
      4,
      4,
      3,
      4,
      3,
      2,
      4,
      1,
      3,
      2,
      4,
      4,
      5,
      2,
      4,
      3,
      2,
      3,
      4,
      4,
      4,
      3,
      4,
      2,
      1,
      3,
      1,
      1,
      4,
      2,
      2,
      3,
      4,
      3,
      4,
      3,
      3,
      2,
      3,
      2,
      3,
      4,
      5,
      3,
      4,
      2,
      3,
      3,
      3,
      3,
      3,
      3,
      5,
      3,
      1,
      1,
      2,
      3,
      1,
      3,
      4,
      4,
      4,
      2,
      1,
      2,
      2,
      3,
      1,
      3,
      2,
      2,
      3,
      3,
      3,
      4,
      2,
      1,
      2,
      2,
      4,
      3,
      2,
      3,
      5,
      3,
      3,
      4,
      3,
      3,
      2,
      2,
      2,
      2,
      3,
      2,
      2,
      2,
      3,
      2,
      2,
      2,
      2,
      2,
      3,
      1,
      3,
      2,
      3,
      1,
      3,
      5,
      5,
      4,
      4,
      3,
      3,
      2,
      4,
      3,
      3,
      4,
      3,
      4,
      2,
      4,
      3,
      4,
      2,
      1,
      2,
      5,
      6,
      3,
      2,
      2,
      2,
      2,
      4,
      2,
      4,
      3,
      3,
      3,
      5,
      3,
      2,
      4,
      4,
      3,
      3,
      4,
      1,
      3,
      4,
      3,
      5,
      4,
      2,
      3,
      2,
      2,
      3,
      4,
      3,
      3,
      2,
      1,
      2,
      2,
      2,
      2,
      1,
      3,
      3,
      4,
      4,
      2,
      3,
      3,
      2,
      2,
      3,
      3,
      2,
      6,
      3,
      3,
      7,
      2,
      2,
      4,
      3,
      6,
      2,
      2,
      2,
      5,
      3,
      1,
      3,
      3,
      2,
      3,
      3,
      2,
      3,
      1,
      2,
      2,
      3,
      3,
      3,
      1,
      2,
      3,
      2,
      3,
      3,
      3,
      3,
      2,
      2,
      2,
      3,
      3,
      3,
      2,
      3,
      4,
      3,
      5,
      3,
      2,
      2,
      3,
      7,
      5,
      2,
      1,
      4,
      3,
      4,
      2,
      3,
      2,
      1,
      2,
      2,
      6,
      4,
      2,
      3,
      2,
      2,
      3,
      2,
      3,
      2,
      3,
      2,
      3,
      1,
      5,
      3,
      3,
      2,
      3,
      2,
      1,
      2,
      3,
      1,
      2,
      4,
      2,
      2,
      2,
      3,
      3,
      2,
      5,
      3,
      2,
      3,
      6,
      2,
      4,
      3,
      4,
      3,
      2,
      3,
      3,
      2,
      4,
      2,
      3,
      3,
      2,
      3,
      5,
      2,
      4,
      3,
      2,
      6,
      4,
      3,
      2,
      3,
      2,
      2,
      1,
      2,
      3,
      4,
      2,
      2,
      1,
      2,
      2,
      2,
      2,
      3,
      3,
      2,
      3,
      4,
      3,
      3,
      1,
      3,
      3,
      2,
      2,
      2,
      4,
      2,
      2,
      2,
      3,
      1,
      3,
      3,
      3,
      3,
      3,
      2,
      4,
      3,
      1,
      3,
      3,
      4,
      3,
      2,
      2,
      3,
      2,
      3,
      5,
      3,
      2,
      2,
      3,
      2,
      1,
      2,
      2,
      1,
      4,
      2,
      3,
      1,
      3,
      2,
      2,
      2,
      2,
      2,
      1,
      3,
      3,
      1,
      2,
      1,
      3,
      5,
      1,
      2,
      1,
      4,
      2,
      5,
      3,
      2,
      2,
      2,
      4,
      2,
      2,
      6,
      4,
      4,
      2,
      2,
      3,
      3,
      4,
      4,
      5,
      4,
      4,
      4,
      2,
      5,
      4,
      1,
      5,
      4,
      1,
      2,
      3,
      2,
      2,
      1,
      3,
      4,
      2,
      5,
      1,
      1,
      3,
      4,
      2,
      3,
      2,
      3,
      4,
      4,
      2,
      3,
      1,
      5,
      2,
      4,
      5,
      4,
      3,
      1,
      5,
      1,
      1,
      1,
      3,
      3,
      5,
      6,
      6,
      5,
      2,
      6,
      3,
      3,
      2,
      2,
      4,
      4,
      2,
      2,
      2,
      5,
      2,
      3,
      1,
      5,
      4,
      3,
      5,
      5,
      3,
      3,
      3,
      3,
      3,
      2,
      3,
      4,
      2,
      3,
      2,
      3,
      3,
      3,
      3,
      2,
      3,
      1,
      3,
      3,
      5,
      3,
      2,
      2,
      3,
      6,
      3,
      6,
      3,
      4,
      3,
      4,
      3,
      4,
      2,
      3,
      3,
      3,
      2,
      2,
      2,
      4,
      2,
      3,
      4,
      3,
      1,
      3,
      1,
      3,
      3,
      2,
      1,
      3,
      3,
      3,
      2,
      4,
      4,
      3,
      3,
      4,
      4,
      4,
      3,
      2,
      3,
      3,
      1,
      2,
      2,
      1,
      4,
      3,
      3,
      5,
      2,
      3,
      3,
      4,
      3,
      3,
      2,
      2,
      3,
      2,
      3,
      4,
      4,
      3,
      4,
      3,
      3,
      3,
      4,
      2,
      3,
      3,
      3,
      1,
      3,
      1,
      3,
      4,
      5,
      4,
      2,
      4,
      2,
      4,
      3,
      2,
      1,
      2,
      4,
      4,
      3,
      2,
      2,
      2,
      3,
      3,
      4,
      3,
      3,
      3,
      2,
      2,
      3,
      2,
      1,
      3,
      4,
      3,
      4,
      2,
      1,
      3,
      1,
      3,
      4,
      3,
      3,
      1,
      3,
      1,
      4,
      3,
      2,
      3,
      3,
      2,
      5,
      4,
      1,
      5,
      5,
      2,
      3,
      2,
      3,
      3,
      2,
      4,
      2,
      2,
      3,
      5,
      6,
      4,
      4,
      2,
      3,
      1,
      1,
      2,
      4,
      2,
      3,
      3,
      3,
      5,
      3,
      2,
      4,
      3,
      1,
      2,
      4,
      5,
      2,
      2,
      5,
      6,
      2,
      2,
      3,
      3,
      2,
      2,
      2,
      3,
      2,
      2,
      4,
      6,
      2,
      4,
      2,
      2,
      3,
      8,
      5,
      1,
      3,
      2,
      4,
      2,
      4,
      2,
      3,
      2,
      3,
      3,
      3,
      2,
      4,
      2,
      2,
      2,
      3,
      2,
      3,
      4,
      3,
      3,
      5,
      2,
      2,
      3,
      2,
      3,
      1,
      6,
      3,
      2,
      3,
      4,
      3,
      1,
      2,
      5,
      4,
      1,
      4,
      2,
      2,
      2,
      2,
      1,
      3,
      3,
      3,
      3,
      3,
      4,
      3,
      4,
      2,
      2,
      3,
      4,
      2,
      1,
      3,
      3,
      4,
      3,
      2,
      2,
      4,
      1,
      2,
      1,
      3,
      4,
      7,
      3,
      4,
      3,
      4,
      3,
      1,
      2,
      2,
      3,
      4,
      3,
      4,
      2,
      1,
      3,
      2,
      3,
      3,
      3,
      3,
      3,
      4,
      2,
      5,
      5,
      3,
      3,
      3,
      3,
      2,
      3,
      4,
      3,
      1,
      2,
      2,
      2,
      3,
      5,
      2,
      2,
      3,
      1,
      2,
      4,
      4,
      5,
      4,
      3,
      3,
      4,
      2,
      1,
      2,
      4,
      2,
      3,
      3,
      3,
      6,
      3,
      3,
      1,
      1,
      1,
      3,
      3,
      2,
      4,
      1,
      4,
      4,
      5,
      3,
      3,
      2,
      4,
      3,
      4,
      6,
      1,
      2,
      3,
      4,
      1,
      2,
      5,
      2,
      2,
      3,
      3,
      2,
      3,
      3,
      5,
      4,
      3,
      2,
      2,
      3,
      3,
      2,
      2,
      5,
      2,
      2,
      3,
      3,
      2,
      3,
      4,
      4,
      4,
      1,
      2,
      4,
      3,
      1,
      3,
      4,
      4,
      3,
      1,
      3,
      3,
      4,
      2,
      4,
      1,
      4,
      3,
      2,
      1,
      4,
      3,
      2,
      2,
      6,
      3,
      3,
      3,
      4,
      4,
      2,
      3,
      4,
      1,
      3,
      4,
      1,
      3,
      2,
      2,
      2,
      2,
      1,
      2,
      3,
      5,
      2,
      2,
      3,
      2,
      2,
      3,
      4,
      2,
      2,
      2,
      1,
      5,
      2,
      5,
      3,
      3,
      3,
      5,
      1,
      4,
      3,
      5,
      4,
      3,
      3,
      3,
      2,
      3,
      3,
      3,
      4,
      2,
      3,
      2,
      4,
      3,
      2,
      2,
      3,
      3,
      2,
      2,
      4,
      2,
      2,
      2,
      3,
      4,
      2,
      4,
      4,
      2,
      4,
      2,
      2,
      4,
      3,
      3,
      4,
      3,
      2,
      1,
      5,
      2,
      3,
      2,
      2,
      3,
      4,
      4,
      1,
      3,
      1,
      3,
      2,
      4,
      2,
      5,
      2,
      4,
      2,
      2,
      2,
      2,
      2,
      2,
      3,
      1,
      1,
      2,
      2,
      1,
      2,
      3,
      3,
      3,
      1,
      4,
      4,
      1,
      2,
      3,
      2,
      2,
      2,
      3,
      3,
      2,
      2,
      2,
      4,
      3,
      1,
      3,
      3,
      3,
      2,
      4,
      4,
      2,
      4,
      3,
      3,
      3,
      2,
      4,
      3,
      4,
      3,
      1,
      3,
      2,
      3,
      3,
      4,
      2,
      5,
      2,
      5,
      2,
      4,
      4,
      2,
      3,
      1,
      2,
      3,
      4,
      2,
      2,
      2,
      4,
      1,
      4,
      3,
      2,
      5,
      2,
      3,
      6,
      3,
      5,
      4,
      2,
      2,
      3,
      3,
      2,
      3,
      3,
      2,
      4,
      3,
      4,
      3,
      2,
      1,
      2,
      2,
      4,
      1,
      1,
      2,
      2,
      1,
      3,
      4,
      3,
      1,
      2,
      2,
      2,
      3,
      3,
      5,
      5,
      4,
      3,
      3,
      4,
      2,
      4,
      5,
      3,
      1,
      3,
      1,
      3,
      2,
      2,
      5,
      3,
      3,
      3,
      4,
      4,
      3,
      1,
      3,
      3,
      6,
      2,
      3,
      3,
      3,
      1,
      3,
      2,
      3,
      3,
      3,
      3,
      1,
      2,
      3,
      2,
      2,
      3,
      3,
      4,
      5,
      2,
      4,
      7,
      4,
      3,
      4,
      5,
      2,
      4,
      2,
      6,
      2,
      4,
      2,
      3,
      4,
      3,
      1,
      2,
      3,
      3,
      3,
      2,
      3,
      2,
      3,
      5,
      4,
      2,
      4,
      3,
      3,
      1,
      3,
      3,
      2,
      2,
      2,
      1,
      3,
      2,
      2,
      4,
      3,
      3,
      2,
      5,
      3,
      3,
      2,
      2,
      2,
      2,
      2,
      3,
      3,
      4,
      4,
      4,
      2,
      2,
      5,
      6,
      5,
      4,
      2,
      5,
      4,
      3,
      4,
      1,
      3,
      3,
      3,
      2,
      2,
      1,
      4,
      1,
      2,
      2,
      3,
      3,
      3,
      3,
      3,
      2,
      3,
      1,
      1,
      3,
      3,
      3,
      2,
      5,
      4,
      2,
      4,
      4,
      3,
      1,
      2,
      3,
      2,
      2,
      3,
      2,
      2,
      4,
      3,
      1,
      3,
      1,
      4,
      3,
      3,
      3,
      4,
      2,
      3,
      3,
      2,
      1,
      5,
      2,
      2,
      3,
      1,
      2,
      1,
      2,
      3,
      3,
      4,
      3,
      2,
      2,
      3,
      2,
      3,
      2,
      1,
      3,
      3,
      3,
      5,
      4,
      2,
      3,
      1,
      2,
      4,
      2,
      1,
      3,
      2,
      2,
      4,
      3,
      3,
      2,
      2,
      3,
      5,
      1,
      4,
      2,
      2,
      2,
      3,
      2,
      3,
      3,
      2,
      2,
      1,
      1,
      3,
      1,
      2,
      5,
      2,
      4,
      4,
      1,
      2,
      3,
      4,
      4,
      3,
      3,
      1,
      2,
      1,
      4,
      2,
      4,
      2,
      1,
      2,
      1,
      2,
      3,
      2,
      1,
      2,
      3,
      3,
      3,
      3,
      4,
      4,
      2,
      2,
      2,
      3,
      2,
      2,
      2,
      2,
      4,
      1,
      3,
      3,
      3,
      2,
      4,
      2,
      3,
      3,
      3,
      4,
      5,
      3,
      2,
      4,
      1,
      4,
      3,
      1,
      3,
      4,
      2,
      4,
      3,
      2,
      2,
      3,
      2,
      3,
      2,
      4,
      4,
      3,
      2,
      4,
      5,
      2,
      2,
      2,
      4,
      2,
      3,
      2,
      1,
      2,
      2,
      3,
      4,
      1,
      1,
      4,
      3,
      2,
      3,
      3,
      2,
      2,
      3,
      4,
      1,
      5,
      1,
      4,
      1,
      2,
      2,
      1,
      2,
      1,
      4,
      2,
      1,
      2,
      1,
      1,
      3,
      4,
      4,
      4,
      7,
      4,
      3,
      5,
      2,
      8,
      3,
      2,
      4,
      3,
      4,
      2,
      3,
      3,
      2,
      3,
      3,
      2,
      3,
      3,
      3,
      5,
      3,
      1,
      4,
      2,
      3,
      3,
      3,
      3,
      5,
      2,
      2,
      3,
      5,
      6,
      3,
      4,
      5,
      3,
      5,
      2,
      1,
      2,
      2,
      5,
      2,
      3,
      3,
      4,
      3,
      2,
      3,
      4,
      3,
      2,
      1,
      4,
      2,
      4,
      2,
      3,
      1,
      1,
      3,
      2,
      4,
      2,
      3,
      3,
      1,
      1,
      3,
      5,
      3,
      3,
      6,
      2,
      4,
      4,
      4,
      3,
      2,
      5,
      2,
      4,
      3,
      2,
      2,
      3,
      2,
      4,
      3,
      3,
      3,
      2,
      2,
      4,
      1,
      3,
      1,
      4,
      5,
      2,
      4,
      3,
      3,
      3,
      3,
      1,
      3,
      2,
      5,
      3,
      5,
      2,
      2,
      6,
      4,
      2,
      5,
      3,
      4,
      1,
      1,
      2,
      1,
      3,
      2,
      2,
      3,
      3,
      2,
      3,
      4,
      5,
      3,
      2,
      2,
      3,
      2,
      3,
      5,
      4,
      2,
      1,
      5,
      5,
      3,
      2,
      4,
      2,
      3,
      3,
      2,
      3,
      3,
      4,
      3,
      3,
      2,
      3,
      2,
      5,
      1,
      3,
      2,
      1,
      4,
      2,
      2,
      4,
      2,
      2,
      3,
      3,
      2,
      2,
      3,
      3,
      5,
      3,
      1,
      2,
      3,
      3,
      2,
      6,
      2,
      2,
      2,
      2,
      2,
      3,
      4,
      5,
      1,
      2,
      2,
      4,
      4,
      3,
      3,
      2,
      4,
      4,
      2,
      3,
      1,
      3,
      5,
      1,
      3,
      3,
      4,
      4,
      3,
      2,
      3,
      3,
      1,
      1,
      3,
      2,
      2,
      4,
      2,
      4,
      3,
      5,
      4,
      3,
      1,
      5,
      2,
      2,
      3,
      1,
      3,
      4,
      4,
      3,
      3,
      3,
      3,
      2,
      1,
      3,
      2,
      1,
      1,
      4,
      2,
      1,
      3,
      2,
      1,
      5,
      1,
      2,
      3,
      3,
      5,
      4,
      3,
      2,
      3,
      3,
      5,
      3,
      4,
      3,
      3,
      2,
      3,
      4,
      3,
      3,
      1,
      3,
      2,
      3,
      3,
      3,
      4,
      3,
      2,
      3,
      3,
      5,
      5,
      3,
      3,
      2,
      1,
      4,
      2,
      4,
      1,
      2,
      2,
      2,
      3,
      3,
      3,
      2,
      1,
      2,
      3,
      5,
      3,
      5,
      5,
      5,
      6,
      4,
      3,
      1,
      2,
      2,
      2,
      3,
      2,
      2,
      2,
      2,
      2,
      1,
      4,
      3,
      2,
      2,
      2,
      2,
      3,
      2,
      3,
      2,
      1,
      1,
      1,
      3,
      2,
      5,
      2,
      2,
      3,
      3,
      2,
      3,
      2,
      4,
      5,
      3,
      3,
      2,
      3,
      6,
      4,
      5,
      3,
      2,
      2,
      1,
      3,
      3,
      4,
      3,
      2,
      4,
      2,
      4,
      2,
      3,
      3,
      2,
      2,
      3,
      3,
      2,
      2,
      4,
      1,
      3,
      3,
      4,
      3,
      2,
      2,
      4,
      2,
      3,
      2,
      4,
      2,
      2,
      4,
      3,
      3,
      2,
      1,
      3,
      2,
      3,
      4,
      2,
      2,
      3,
      3,
      3,
      1,
      3,
      1,
      5,
      4,
      3,
      3,
      2,
      3,
      3,
      2,
      3,
      1,
      3,
      1,
      3,
      2,
      7,
      2,
      2,
      4,
      2,
      2,
      2,
      4,
      1,
      1,
      2,
      3,
      3,
      2,
      3,
      2,
      3,
      2,
      6,
      4,
      3,
      1,
      6,
      4,
      2,
      3,
      5,
      5,
      2,
      2,
      1,
      4,
      3,
      3,
      4,
      4,
      4,
      2,
      4,
      2,
      3,
      3,
      4,
      7,
      4,
      3,
      2,
      4,
      2,
      3,
      3,
      4,
      4,
      2,
      5,
      2,
      4,
      2,
      2,
      3,
      3,
      4,
      3,
      2,
      2,
      3,
      2,
      5,
      5,
      3,
      1,
      2,
      5,
      3,
      1,
      3,
      3,
      3,
      5,
      1,
      4,
      2,
      2,
      3,
      1,
      2,
      1,
      3,
      5,
      2,
      3,
      3,
      3,
      1,
      3,
      3,
      1,
      2,
      4,
      3,
      4,
      6,
      2,
      2,
      1,
      2,
      3,
      4,
      4,
      1,
      2,
      4,
      4,
      1,
      3,
      3,
      2,
      2,
      4,
      2,
      4,
      2,
      3,
      4,
      2,
      4,
      2,
      4,
      2,
      3,
      3,
      3,
      5,
      1,
      5,
      3,
      3,
      3,
      2,
      2,
      4,
      4,
      4,
      2,
      4,
      5,
      3,
      4,
      3,
      1,
      2,
      5,
      3,
      3,
      3,
      5,
      1,
      2,
      6,
      4,
      4,
      5,
      3,
      2,
      2,
      2,
      3,
      3,
      2,
      3,
      6,
      3,
      4,
      2,
      2,
      3,
      2,
      4,
      2,
      5,
      2,
      4,
      1,
      3,
      2,
      2,
      3,
      4,
      3,
      3,
      3,
      2,
      3,
      4,
      4,
      2,
      3,
      3,
      3,
      1,
      3,
      2,
      2,
      1,
      2,
      3,
      4,
      2,
      3,
      2,
      6,
      2,
      3,
      1,
      4,
      3,
      3,
      2,
      2,
      1,
      3,
      3,
      3,
      3,
      3,
      4,
      2,
      3,
      2,
      1,
      2,
      3,
      1,
      4,
      4,
      3,
      1,
      4,
      3,
      3,
      5,
      3,
      4,
      4,
      2,
      3,
      5,
      2,
      3,
      4,
      2,
      1,
      3,
      3,
      3,
      3,
      2,
      3,
      3,
      5,
      3,
      3,
      4,
      5,
      2,
      4,
      1,
      2,
      3,
      3,
      3,
      1,
      2,
      1,
      3,
      3,
      2,
      2,
      2,
      4,
      2,
      3,
      2,
      3,
      4,
      3,
      2,
      2,
      3,
      2,
      2,
      3,
      5,
      3,
      3,
      3,
      3,
      2,
      1,
      6,
      2,
      4,
      4,
      3,
      4
    ]
  },
  "sentence_ending_metrics": {
    "noun_style_count": 13,
    "copula_style_count": 77,
    "verb_style_count": 307,
    "other_style_count": 59,
    "noun_style_ratio": 0.02850877192982456,
    "copula_style_ratio": 0.16885964912280702,
    "verb_style_ratio": 0.6732456140350878,
    "other_style_ratio": 0.12938596491228072
  },
  "lexical_metrics": {
    "total_morphemes": 8588,
    "unique_morphemes": 1706,
    "ttr": 0.19864927806241267,
    "noun_ttr": 0.35927557513460595,
    "verb_ttr": 0.29519071310116085
  },
  "pos_class_frequencies": {
    "nouns_freq": 2043,
    "verbs_freq": 1068,
    "adjectives_freq": 138,
    "modifiers_freq": 526,
    "particles_freq": 1330,
    "endings_freq": 1914,
    "nng_freq": 1573,
    "nnb_freq": 167,
    "vv_freq": 829,
    "vx_verb_freq": 239,
    "va_freq": 138,
    "vx_adj_freq": 0,
    "etm_freq": 390,
    "etn_freq": 47
  },
  "specialized_frequencies": {
    "ending_morphemes": {
      "다/EF": 179,
      "ᆫ다/EF": 61,
      "는다/EF": 15,
      "ᆯ까/EF": 5,
      "리라/EF": 4,
      "니/EF": 5,
      "예요/EF": 1,
      "어요/EF": 8,
      "어/EF": 32,
      "냐/EF": 6,
      "더라구/EF": 2,
      "다며/EF": 1,
      "다구/EF": 2,
      "디/EF": 1,
      "야/EF": 19,
      "자/EF": 1,
      "다면서/EF": 1,
      "어라/EF": 7,
      "지/EF": 12,
      "네/EF": 3,
      "다나/EF": 1,
      "더라야/EF": 1,
      "대/EF": 2,
      "거든/EF": 2,
      "ᆫ걸/EF": 1,
      "ᆫ다구/EF": 1,
      "더라/EF": 1,
      "을까/EF": 3,
      "어야지/EF": 1,
      "단가/EF": 3,
      "ᆫ단다/EF": 1,
      "구나/EF": 1,
      "ᆫ가/EF": 1,
      "여/EF": 1,
      "으까/EF": 1,
      "고/EF": 1,
      "애/EF": 1,
      "ᆫ데/EF": 2,
      "어서/EF": 1,
      "습니까/EF": 1,
      "는데요/EF": 1,
      "죠/EF": 4,
      "ᆫ데요/EF": 1,
      "거든요/EF": 1,
      "ᆸ니다요/EF": 1,
      "나요/EF": 1,
      "에요/EF": 1,
      "지요/EF": 1,
      "다니까요/EF": 1,
      "ᆫ댄다/EF": 1,
      "으니까/EF": 1,
      "잖아/EF": 4,
      "라구/EF": 1,
      "더라구요/EF": 1,
      "으니까요/EF": 2,
      "래/EF": 1,
      "구만/EF": 1,
      "세요/EF": 1,
      "라구요/EF": 1,
      "으리라/EF": 1
    },
    "punctuations": {
      "《/SSO": 1,
      "》/SSC": 1,
      "./SF": 402,
      "Y/SL": 8,
      ",/SP": 147,
      "……/SE": 6,
      "114/SN": 1,
      "K/SL": 5,
      "“/SSO": 108,
      "?/SF": 56,
      "”/SSC": 108,
      "!/SF": 4,
      "'/SSO": 3,
      "'/SSC": 3,
      "‘/SSO": 3,
      "’/SSC": 3
    },
    "etm_detail_freq": {
      "은/ETM": 37,
      "ᆫ/ETM": 126,
      "는/ETM": 118,
      "다는/ETM": 7,
      "ᆯ/ETM": 51,
      "라는/ETM": 4,
      "던/ETM": 24,
      "ᆫ다는/ETM": 1,
      "을/ETM": 17,
      "느냐는/ETM": 1,
      "란/ETM": 3,
      "냐는/ETM": 1
    },
    "etn_detail_freq": {
      "기/ETN": 36,
      "ᆷ/ETN": 6,
      "음/ETN": 5
    }
  },
  "morpheme_frequencies": {
    "《/SSO": 1,
    "아무/NP": 6,
    "도/JX": 84,
    "기다리/VV": 7,
    "지/EC": 54,
    "않/VX": 35,
    "었/EP": 240,
    "다/EF": 179,
    "》/SSC": 1,
    "하필/MAG": 1,
    "이사/NNG": 4,
    "날짜/NNG": 2,
    "잡/VV-R": 5,
    "은/ETM": 37,
    "날/NNG": 7,
    "눈/NNG": 12,
    "이/JKS": 176,
    "내리/VV": 3,
    "./SF": 402,
    "폭설/NNG": 1,
    "이/VCP": 159,
    "이삿짐/NNG": 1,
    "차/NNG": 2,
    "는/JX": 144,
    "그/MM": 44,
    "을/JKO": 136,
    "함빡/MAG": 1,
    "뒤집어쓰/VV": 1,
    "ᆫ/ETM": 126,
    "채/NNB": 2,
    "Y/SL": 8,
    "시/NNG": 8,
    "를/JKO": 94,
    "향하/VV": 2,
    "어/EC": 162,
    "고속/NNG": 1,
    "도로/NNG": 1,
    "와/JC": 5,
    "국도/NNG": 1,
    "달리/VV": 1,
    "시/NNB": 4,
    "가/JKS": 151,
    "가깝/VA-I": 1,
    "지/VX": 13,
    "자/EC": 6,
    "눈발/NNG": 1,
    "점점/MAG": 1,
    "성글/VA": 1,
    "더니/EC": 3,
    "어디/NP": 15,
    "쯤/XSN": 5,
    "에서/JKB": 24,
    "ᆫ가/EC": 8,
    "부터/JX": 2,
    "은/JX": 54,
    "거짓말/NNG": 1,
    "처럼/JKB": 8,
    "뚝/MAG": 2,
    "그치/VV": 1,
    "있/VX": 40,
    "그리고/MAJ": 5,
    "시내/NNG": 2,
    "로/JKB": 29,
    "들어서/VV": 5,
    "자마자/EC": 4,
    "에/JKB": 130,
    "띄/VV": 2,
    "는/ETM": 118,
    "것/NNB": 49,
    "빨갛/VA-I": 1,
    "동백꽃/NNG": 1,
    "가로수/NNG": 1,
    "심/VV": 1,
    "나무/NNG": 1,
    "의/JKG": 60,
    "파랗/VA-I": 1,
    "잎사귀/NNG": 1,
    "사이/NNG": 2,
    "붉/VA": 2,
    "꽃/NNG": 2,
    "들/XSN": 111,
    "만발/NNG": 1,
    "하/XSV": 57,
    "조금/MAG": 2,
    "낯설/VA": 3,
    "기/ETN": 36,
    "ᆫ/JX": 27,
    "하/VX": 36,
    "지만/EC": 11,
    "경희/NNP": 60,
    "그렇/VA-I": 32,
    "어도/EC": 10,
    "보/VV": 22,
    "마음/NNG": 5,
    "포근/XR": 1,
    "하/XSA": 74,
    "집안/NNG": 3,
    "정리/NNG": 5,
    "데/NNB": 6,
    "근/MM": 1,
    "일주일/NNG": 1,
    "이상/NNG": 2,
    "걸리/VV": 3,
    "동안/NNG": 5,
    "남편/NNG": 32,
    "한테서/JKB": 6,
    "전혀/MAG": 2,
    "연락/NNG": 1,
    "오/VV": 39,
    "한편/NNG": 1,
    "으로/JKB": 30,
    "비장/XR": 3,
    "집/NNG": 41,
    "하/VV": 110,
    "오히려/MAG": 2,
    "ᆷ/ETN": 6,
    "그네/NP": 20,
    "차분/XR": 1,
    "게/EC": 54,
    "같/VA": 9,
    "텔레비전/NNG": 11,
    "과/JC": 2,
    "비디오/NNG": 1,
    ",/SP": 147,
    "오디오/NNG": 1,
    "선/NNG": 4,
    "어떻/VA-I": 4,
    "연결/NNG": 2,
    "ᆯ지/EC": 1,
    "모르/VV": 20,
    "그대로/MAG": 4,
    "두/VV": 5,
    "다가/EC": 8,
    "대충/MAG": 1,
    "끝나/VV": 4,
    "맘/NNG": 2,
    "고/EC": 139,
    "이/MM": 9,
    "저/MM": 3,
    "얼키설키/MAG": 1,
    "전기/NNG": 2,
    "코드/NNG": 3,
    "꽂/VV": 3,
    "엄마/NNG": 55,
    "ᆫ다고/EC": 4,
    "북적대/VV": 1,
    "와중/NNG": 2,
    "아이/NNG": 62,
    "컴퓨터/NNG": 18,
    "는지/EC": 14,
    "게임/NNG": 4,
    "느라고/EC": 1,
    "정신/NNG": 1,
    "없/VA": 29,
    "정신없이/MAG": 1,
    "빠지/VV": 5,
    "순간/NNG": 6,
    "거실/NNG": 2,
    "쪽/NNB": 2,
    "느닷없이/MAG": 1,
    "나가/VV": 12,
    "무슨/MM": 7,
    "일/NNG": 21,
    "ᆫ지/EC": 7,
    "누전/NNG": 1,
    "차단기/NNG": 2,
    "내려가/VV": 1,
    "다시/MAG": 7,
    "올리/VV": 1,
    "조심스레/MAG": 2,
    "는데/EC": 17,
    "다행히/MAG": 2,
    "별일/NNG": 1,
    "그런데/MAJ": 4,
    "방/NNG": 1,
    "비명/NNG": 2,
    "터지/VV": 1,
    "나오/VV": 8,
    "파워/NNG": 1,
    "버리/VX": 8,
    "다는/ETM": 7,
    "숫제/MAG": 2,
    "두/MM": 5,
    "발/NNG": 1,
    "동동/MAG": 1,
    "구르/VV": 1,
    "혼자/NNG": 6,
    "짐/NNG": 3,
    "옮기/VV": 2,
    "ᆯ/ETM": 51,
    "때/NNG": 33,
    "하마터면/MAG": 1,
    "더미/NNG": 1,
    "깔리/VV": 1,
    "뻔/NNB": 1,
    "내색/NNG": 1,
    "안/MAG": 26,
    "저희/NP": 2,
    "무겁/VA-I": 1,
    "겨우/MAG": 2,
    "돕/VV-I": 1,
    "주/VX": 18,
    "시늉/NNG": 1,
    "만/JX": 21,
    "앞/NNG": 10,
    "쪼르르/MAG": 2,
    "달려가/VV": 1,
    "바쁘/VA": 1,
    "더니만/EC": 1,
    "사/VV": 8,
    "사람/NNG": 19,
    "나/NP": 27,
    "ᆫ데/EC": 9,
    "……/SE": 6,
    "모습/NNG": 5,
    "억장/NNG": 1,
    "무너지/VV": 1,
    "면서/EC": 8,
    "서러움/NNG": 1,
    "복받치/VV": 1,
    "ᆫ다/EF": 61,
    "이제/MAG": 8,
    "열/NR": 2,
    "살/NNB": 5,
    "짜리/XSN": 1,
    "남매/NNG": 1,
    "으면/EC": 8,
    "이란/JX": 4,
    "싸움/NNG": 1,
    "질/XSN": 2,
    "라/EC": 7,
    "차라리/MAG": 2,
    "앉/VV": 5,
    "속/NNG": 10,
    "편하/VA": 1,
    "점/NNG": 2,
    "새/NNG": 2,
    "못/MAG": 9,
    "참/VV": 1,
    "고치/VV": 7,
    "내/VX": 4,
    "라고/EC": 26,
    "성화/NNG": 1,
    "부리/VV": 1,
    "그만/MAG": 6,
    "지르/VV": 1,
    "말/VX": 16,
    "징글징글/MAG": 1,
    "거/NNB": 24,
    "새끼/NNG": 3,
    "114/SN": 1,
    "있/VV": 15,
    "마다/JX": 5,
    "전화/NNG": 10,
    "수리/NNG": 1,
    "기사/NNG": 1,
    "전부/MAG": 1,
    "설/NNG": 16,
    "쇠/VV": 4,
    "러/EC": 8,
    "가/VV": 25,
    "다고/EC": 12,
    "그래도/MAJ": 11,
    "그렇게/MAG": 1,
    "어서/EC": 28,
    "얻/VV-R": 3,
    "정보/NNG": 1,
    "다면/EC": 1,
    "오늘/NNG": 3,
    "중/NNB": 4,
    "려면/EC": 1,
    "대/XPN": 2,
    "규모/NNG": 1,
    "전자/NNG": 2,
    "상가/NNG": 2,
    "K/SL": 5,
    "까지/JX": 10,
    "보/VX": 18,
    "라는/ETM": 4,
    "말/NNG": 34,
    "그리하여/MAJ": 1,
    "막/MAG": 5,
    "살/VV": 13,
    "시작/NNG": 4,
    "로부터/JKB": 2,
    "시간/NNG": 3,
    "떨어지/VV": 4,
    "장정/NNG": 1,
    "길/NNG": 5,
    "오르/VV": 1,
    "막내/NNG": 5,
    "아직/MAG": 4,
    "어린아이/NNG": 1,
    "라서/EC": 1,
    "데리/VV": 2,
    "둘째/NR": 2,
    "누나/NNG": 1,
    "하고/JKB": 7,
    "단/MM": 1,
    "둘/NR": 1,
    "싫/VA": 8,
    "큰애/NNG": 2,
    "또/MAG": 10,
    "저/NP": 6,
    "사촌/NNG": 4,
    "만나/VV": 3,
    "생각/NNG": 9,
    "따라나서/VV": 1,
    "마치/MAG": 1,
    "할머니/NNG": 1,
    "고서/EC": 3,
    "그/NP": 18,
    "네/XSN": 8,
    "가족/NNG": 2,
    "모/VV": 1,
    "고물/NNG": 1,
    "티코/NNP": 1,
    "타/VV": 3,
    "출발/NNG": 1,
    "나/VX": 7,
    "서/VV": 6,
    "대목/NNG": 1,
    "그냥/MAG": 5,
    "되돌아가/VV": 1,
    "허전/XR": 2,
    "옆/NNG": 4,
    "백화점/NNG": 1,
    "몇/MM": 3,
    "가지/NNB": 1,
    "식품/NNG": 1,
    "떡국/NNG": 1,
    "떡/NNG": 1,
    "한/MM": 17,
    "봉지/NNG": 1,
    "쇠고기/NNG": 1,
    "만/NR": 1,
    "원/NNB": 1,
    "어치/XSN": 1,
    "나물/NNG": 1,
    "류/XSN": 1,
    "생선/NNG": 2,
    "과자/NNG": 1,
    "좀/MAG": 8,
    "음식/NNG": 3,
    "준비/NNG": 2,
    "재료/NNG": 1,
    "충분/XR": 1,
    "옷/NNG": 3,
    "달/VX": 3,
    "칭얼대/VV": 2,
    "자장면/NNG": 1,
    "그릇/NNG": 1,
    "씩/XSN": 4,
    "입막음/NNG": 1,
    "뭐/NP": 14,
    "도시/NNG": 1,
    "언니/NNG": 31,
    "ᆯ/JKO": 11,
    "들르/VV": 2,
    "늘상/MAG": 2,
    "듯이/EC": 1,
    "있/VA": 6,
    "방학/NNG": 1,
    "내내/MAG": 2,
    "만판/MAG": 1,
    "어미/NNG": 6,
    "맡기/VV": 1,
    "놓/VX": 7,
    "밖/NNG": 3,
    "돈/NNG": 4,
    "벌/VV": 2,
    "그러/VV": 11,
    "니/EC": 16,
    "고맙/VA-I": 2,
    "든든/XR": 1,
    "어른/NNG": 2,
    "놔두/VV": 1,
    "수시로/MAG": 1,
    "걸어오/VV": 1,
    "마침/MAG": 2,
    "조카/NNG": 3,
    "받/VV-R": 4,
    "는다/EF": 15,
    "이모/NNG": 2,
    "냉큼/MAG": 1,
    "알리/VV": 1,
    "고기/NNG": 1,
    "하고/JC": 2,
    "덜/VV": 1,
    "려고/EC": 5,
    "바꾸/VV": 1,
    "전화선/NNG": 1,
    "저쪽/NP": 1,
    "자기/NP": 4,
    "저녁/NNG": 3,
    "먹/VV": 11,
    "또래/NNG": 1,
    "마냥/MAG": 1,
    "신나/VV": 1,
    "대로/JX": 5,
    "네/MM": 2,
    "배기/XSN": 1,
    "끌어안/VV": 1,
    "기다랗/VA-I": 1,
    "눕/VV-I": 3,
    "피붙이/NNG": 1,
    "왜/MAG": 21,
    "눈물/NNG": 8,
    "나/VV": 14,
    "ᆯ까/EF": 5,
    "눈꼬리/NNG": 1,
    "추적/NNG": 1,
    "달라붙/VV": 3,
    "이런/MM": 2,
    "외할머니/NNG": 2,
    "눈가/NNG": 3,
    "잘/MAG": 8,
    "붙/VV": 4,
    "와/JKB": 4,
    "똑같이/MAG": 1,
    "던/ETM": 24,
    "그것/NP": 13,
    "얼굴/NNG": 4,
    "빤히/MAG": 1,
    "바라보/VV": 3,
    "손등/NNG": 1,
    "쓱/MAG": 1,
    "닦/VV": 3,
    "사랑/NNG": 3,
    "뜻/NNG": 3,
    "꼭/MAG": 5,
    "안/VV": 1,
    "삶/NNG": 1,
    "힘들/VA": 3,
    "남루/NNG": 1,
    "적/XSN": 3,
    "왕비/NNG": 1,
    "가/JKC": 8,
    "되/VV": 24,
    "가장/MAG": 5,
    "행복/NNG": 4,
    "자식/NNG": 9,
    "세상/NNG": 5,
    "모든/MM": 1,
    "다/MAG": 7,
    "그러/XR": 1,
    "듯/EC": 1,
    "땜/NNB": 5,
    "아프/VA": 6,
    "주/VV": 3,
    "그리/MAG": 4,
    "크/VA": 5,
    "느끼/VV": 3,
    "못하/VX": 6,
    "리라/EF": 4,
    "아비/NNG": 2,
    "보다/JKB": 1,
    "더/MAG": 5,
    "행복감/NNG": 1,
    "맛보/VV": 1,
    "ᆫ다면/EC": 1,
    "그거/NP": 5,
    "아마/MAG": 1,
    "출산/NNG": 1,
    "고통/NNG": 1,
    "겪/VV": 1,
    "때문/NNB": 6,
    "이/JKC": 12,
    "아니/VCN": 15,
    "남자/NNG": 9,
    "쾌락/NNG": 1,
    "자의/NNG": 1,
    "다르/VA": 1,
    "만들/VV": 4,
    "여자/NNG": 11,
    "깊/VA": 1,
    "곳/NNG": 1,
    "근본/NNG": 1,
    "욕구/NNG": 2,
    "싶/VX": 7,
    "의하/VV": 1,
    "낳/VV": 2,
    "기르/VV": 1,
    "ᆫ다는/ETM": 1,
    "들/VV": 8,
    "여성/NNG": 3,
    "성/XSN": 5,
    "무어/NP": 1,
    "품/VV": 1,
    "키우/VV": 5,
    "속성/NNG": 1,
    "가지/VV": 4,
    "옹기종기/MAG": 1,
    "만화/NNG": 2,
    "동그랗/VA-I": 1,
    "머리/NNG": 2,
    "새삼스레/MAG": 1,
    "자신/NNG": 6,
    "이나/JC": 2,
    "나/JC": 1,
    "부재/NNG": 1,
    "현란/NNG": 2,
    "움직이/VV": 1,
    "쳐다보/VV": 1,
    "너머/NNG": 2,
    "언뜻/MAG": 1,
    "재떨이/NNG": 1,
    "발견/NNG": 1,
    "꽁초/NNG": 1,
    "서너/MM": 2,
    "개/NNB": 1,
    "구겨지/VV": 1,
    "담뱃갑/NNG": 1,
    "한테/JKB": 28,
    "묻/VV-I": 10,
    "“/SSO": 108,
    "담배/NNG": 3,
    "피우/VV": 3,
    "니/EF": 5,
    "?/SF": 56,
    "”/SSC": 108,
    "오/EC": 1,
    "아빠/NNG": 19,
    "예요/EF": 1,
    "었었/EP": 1,
    "네/IC": 3,
    "짤막/XR": 1,
    "대답/NNG": 6,
    "언제/MAG": 2,
    "며칠/NNG": 1,
    "어요/EF": 8,
    "지금/NNG": 2,
    "시/EP": 9,
    "어/EF": 32,
    "낮/NNG": 1,
    "밤/NNG": 2,
    "들어오/VV": 8,
    "전/NNG": 4,
    "밥/NNG": 6,
    "이라도/JX": 1,
    "으려고/EC": 3,
    "전기밥솥/NNG": 1,
    "씻/VV-R": 4,
    "빙판/NNG": 1,
    "얼마나/MAG": 6,
    "미끄럽/VA-I": 1,
    "은지/EC": 1,
    "차례/NNG": 3,
    "나/JX": 4,
    "엉덩방아/NNG": 2,
    "찧/VV": 4,
    "골반/NNG": 1,
    "뼈/NNG": 1,
    "욱신거리/VV": 1,
    "푸념/NNG": 4,
    "그녀/NP": 4,
    "이즈음/NNG": 1,
    "생활/NNG": 2,
    "설계사/NNG": 1,
    "계약자/NNG": 1,
    "찾/VV": 5,
    "하루/NNG": 3,
    "종일/NNG": 1,
    "사방/NNG": 3,
    "돌아다니/VV": 1,
    "어야/EC": 15,
    "짧/VA": 2,
    "단화/NNG": 2,
    "멋/NNG": 1,
    "취미/NNG": 1,
    "맞/VV": 6,
    "을/ETM": 17,
    "뿐/NNB": 2,
    "직업/NNG": 2,
    "만큼/NNB": 1,
    "말쑥/XR": 1,
    "정장/NNG": 1,
    "차림/NNG": 1,
    "다니/VV": 5,
    "그런/MM": 10,
    "구두/NNG": 1,
    "신/VV": 2,
    "화근/NNG": 1,
    "따뜻/XR": 2,
    "부츠/NNG": 1,
    "여유/NNG": 1,
    "입/NNG": 7,
    "형부/NNG": 6,
    "얘기/NNG": 4,
    "줄창/MAG": 1,
    "보험/NNG": 3,
    "오늘/MAG": 1,
    "비록/MAG": 1,
    "번/NNB": 7,
    "엉/IC": 2,
    "뎅/MAG": 2,
    "이/NNG": 1,
    "다치/VV": 1,
    "보람/NNG": 2,
    "냐/EF": 6,
    "이/XSN": 1,
    "하도/MAG": 2,
    "쉬/VV": 1,
    "어떤/MM": 1,
    "다방/NNG": 1,
    "들어가/VV": 3,
    "세상에/IC": 2,
    "거기/NP": 2,
    "서/JKB": 2,
    "고객/NNG": 1,
    "줄/NNB": 5,
    "이야/JX": 2,
    "누구/NP": 9,
    "알/VV": 22,
    "겠/EP": 14,
    "앙케이트/NNG": 1,
    "ᆯ려고/EC": 1,
    "다가가/VV": 2,
    "자리/NNG": 6,
    "글쎄/IC": 2,
    "턱/MAG": 1,
    "새/MM": 2,
    "시대/NNG": 1,
    "암/NNG": 1,
    "하나/NR": 9,
    "더라구/EF": 2,
    "야/IC": 4,
    "생판/MAG": 1,
    "남/NNG": 3,
    "들어주/VV": 1,
    "어쩜/MAG": 1,
    "너/NP": 6,
    "피/NNG": 3,
    "나누/VV": 1,
    "형제/NNG": 3,
    "가지/VX": 1,
    "소원/NNG": 1,
    "듣/VV-I": 4,
    "그래/IC": 1,
    "그저/MAG": 1,
    "픽/MAG": 1,
    "웃/VV-R": 2,
    "에게/JKB": 2,
    "악감정/NNG": 1,
    "소리/NNG": 10,
    "그야말로/MAG": 1,
    "돌아오/VV": 4,
    "다며/EF": 1,
    "반찬/NNG": 2,
    "조/NNG": 1,
    "물/VV": 2,
    "락/EC": 3,
    "거리/VV": 1,
    "다/EC": 12,
    "슬쩍/MAG": 1,
    "아무/MM": 3,
    "괜히/MAG": 4,
    "무안/NNG": 3,
    "샘물/NNG": 3,
    "다구/EF": 2,
    "딴/MM": 3,
    "디/EF": 1,
    "야/EF": 19,
    "얼른/MAG": 1,
    "자/EF": 1,
    "통/MAG": 1,
    "면/EC": 18,
    "여러/MM": 1,
    "놈/NNB": 2,
    "한꺼번에/MAG": 1,
    "덩키덩키/NNG": 1,
    "재미/NNG": 1,
    "평소/NNG": 1,
    "야무지/VA": 2,
    "대/VX": 5,
    "먹이/VV": 1,
    "큰일/NNG": 1,
    "끝내/VV": 1,
    "기분/NNG": 3,
    "설거지/NNG": 1,
    "커피/NNG": 8,
    "마시/VV": 3,
    "신장/NNG": 1,
    "좋/VA": 9,
    "다면서/EF": 1,
    "이거/NP": 3,
    "이뇨/NNG": 1,
    "작용/NNG": 1,
    "지나치/VA": 2,
    "소변/NNG": 1,
    "자주/MAG": 1,
    "웬/MM": 1,
    "똑똑/XR": 1,
    "니까/EC": 4,
    "연설/NNG": 1,
    "일루/MAG": 1,
    "잔/NNG": 1,
    "어라/EF": 7,
    "자매/NNG": 2,
    "마주/MAG": 1,
    "며/EC": 9,
    "진하/VA": 1,
    "달/VA": 3,
    "내쫓/VV": 1,
    "정말/NNG": 1,
    "대판/NNP": 1,
    "싸우/VV": 3,
    "지/EF": 12,
    "그저께/NNG": 1,
    "어젯밤/NNG": 1,
    "네/EF": 3,
    "천연스레/MAG": 1,
    "아주/MAG": 3,
    "덧붙이/VV": 1,
    "에미/NNG": 1,
    "시키/VV": 3,
    "다나/EC": 1,
    "어쩌/VV": 1,
    "다나/EF": 1,
    "처자식/NNG": 1,
    "돌보/VV": 2,
    "인사/NNG": 3,
    "교육/NNG": 1,
    "되려/MAG": 1,
    "토/NNG": 1,
    "더라야/EF": 1,
    "애비/NNG": 2,
    "폼/NNG": 1,
    "지/NP": 4,
    "노릇/NNG": 2,
    "인간/NNG": 1,
    "종/NNG": 1,
    "대/EF": 2,
    "내/VV": 14,
    "ᆫ들/EC": 3,
    "계집/NNG": 1,
    "오/VX": 4,
    "불쑥불쑥/MAG": 1,
    "내뱉/VV": 1,
    "거칠/VA": 1,
    "들리/VV": 1,
    "ᆯ까/EC": 3,
    "가슴/NNG": 10,
    "철렁/MAG": 2,
    "내려앉/VV": 2,
    "너무/MAG": 7,
    "심하/VA": 1,
    "오죽/MAG": 1,
    "직장/NNG": 1,
    "잃/VV": 1,
    "애/NNG": 23,
    "민망/XR": 1,
    "미안/NNG": 1,
    "그러니까/MAJ": 1,
    "야야/IC": 1,
    "야말로/JX": 1,
    "거든/EF": 2,
    "아이구/IC": 1,
    "뭣/NP": 3,
    "침/NNG": 1,
    "뱉/VV": 1,
    "ᆫ걸/EF": 1,
    "부모/NNG": 3,
    "ᆫ다구/EF": 1,
    "이녁/NNG": 1,
    "오목/MAG": 2,
    "주먹/NNG": 2,
    "콩콩/MAG": 1,
    "세/MM": 2,
    "차이/NNG": 1,
    "그새/NNG": 1,
    "말년/NNG": 1,
    "똑같/VA": 3,
    "손/NNG": 5,
    "않/VV": 1,
    "께/XSN": 1,
    "대/VV": 2,
    "자세/NNG": 3,
    "문득/MAG": 1,
    "생각나/VV": 1,
    "듯이/NNB": 2,
    "복잡/XR": 1,
    "표정/NNG": 3,
    "띠/VV": 1,
    "은밀/XR": 1,
    "아/IC": 3,
    "그년/NP": 1,
    "대뜸/MAG": 1,
    "우리/NP": 6,
    "냄새/NNG": 4,
    "속상하/VA": 2,
    "어요/EC": 1,
    "상황/NNG": 3,
    "로서/JKB": 2,
    "많이/MAG": 2,
    "짐작/NNG": 1,
    "과/JKB": 1,
    "달리/MAG": 1,
    "솔직히/MAG": 1,
    "시원/XR": 1,
    "더라/EF": 1,
    "예전/NNG": 1,
    "아버지/NNG": 29,
    "진정/NNG": 1,
    "을까/EF": 3,
    "몰/VV": 1,
    "섣달/NNG": 3,
    "그믐/NNG": 1,
    "오밤중/NNG": 2,
    "일찍/MAG": 1,
    "세배/NNG": 1,
    "세뱃돈/NNG": 1,
    "챙기/VV": 1,
    "놀/VV": 2,
    "곤/XR": 1,
    "기역/NNG": 1,
    "자/NNG": 1,
    "꼬부라지/VV": 1,
    "곯아떨어지/VV": 1,
    "적막강산/NNG": 1,
    "찾아가/VV": 3,
    "친정/NNG": 2,
    "시댁/NNG": 1,
    "외롭/VA-I": 1,
    "그러나/MAJ": 2,
    "자유/NNG": 1,
    "롭/XSA-I": 1,
    "음/ETN": 5,
    "중간/NNG": 1,
    "고향/NNG": 6,
    "마을/NNG": 4,
    "밤늦/VA": 1,
    "고속도로/NNG": 1,
    "질주/NNG": 1,
    "뒤/NNG": 2,
    "우뚝/MAG": 1,
    "솟/VV-R": 1,
    "낯익/VA": 1,
    "산/NNG": 2,
    "밑/NNG": 3,
    "바로/MAG": 11,
    "랑/JKB": 1,
    "함께/MAG": 1,
    "학교/NNG": 1,
    "친구/NNG": 2,
    "아기/NNG": 2,
    "님/XSN": 2,
    "계시/VX": 1,
    "ᆫ다/EC": 2,
    "명절/NNG": 3,
    "편히/MAG": 1,
    "동네/NNG": 2,
    "수/NNB": 8,
    "을지/EC": 2,
    "딸/NNG": 6,
    "줄줄이/MAG": 1,
    "없이/MAG": 4,
    "부각/NNG": 1,
    "되/XSV": 6,
    "누/NNG": 1,
    "당연/XR": 1,
    "듯/NNB": 3,
    "행방/NNG": 2,
    "물어보/VV": 2,
    "물음/NNG": 1,
    "사실/NNG": 2,
    "용기/NNG": 1,
    "불편/NNG": 3,
    "라도/EC": 3,
    "계시/VV": 1,
    "나이/NNG": 1,
    "미혼자/NNG": 1,
    "나/EC": 11,
    "이혼/NNG": 2,
    "자/XSN": 1,
    "사별/NNG": 2,
    "가난/NNG": 1,
    "몸/NNG": 4,
    "실향민/NNG": 1,
    "노인/NNG": 1,
    "하여간/MAG": 2,
    "부족/NNG": 1,
    "불편부당/NNG": 1,
    "틀림없/VA": 2,
    "반대/NNG": 2,
    "많/VA": 5,
    "권력/NNG": 1,
    "세/VA": 1,
    "건강/NNG": 1,
    "아들/NNG": 1,
    "부부/NNG": 1,
    "축복/NNG": 1,
    "가득/MAG": 1,
    "빌어먹을/IC": 2,
    "라지만/EC": 1,
    "운/NNG": 1,
    "설/NNB": 3,
    "ᆫ고/EC": 1,
    "허/VV": 3,
    "워/NNG": 1,
    "서/NNG": 1,
    "고구마/NNG": 1,
    "조청/NNG": 4,
    "양은/NNG": 1,
    "냄비/NNG": 1,
    "고/VV": 1,
    "솥단지/NNG": 4,
    "구멍/NNG": 3,
    "들러붙/VV": 2,
    "숟가락/NNG": 1,
    "딱딱/MAG": 1,
    "긁/VV": 2,
    "에라/IC": 1,
    "아/JKV": 6,
    "넘/VV": 1,
    "느냐/EC": 1,
    "고/NNG": 1,
    "두세/MM": 2,
    "늘어놓/VV": 1,
    "선잠/NNG": 1,
    "깨어나/VV": 1,
    "혹시/MAG": 2,
    "철커덕/MAG": 1,
    "서울/NNP": 3,
    "부끄럽/VA-I": 9,
    "을까/EC": 1,
    "지나/VV": 2,
    "그믐밤/NNG": 2,
    "도착/NNG": 1,
    "포마드/NNG": 1,
    "향기/NNG": 1,
    "솔솔/MAG": 1,
    "풍기/VV": 2,
    "친아버지/NNG": 1,
    "오래/MAG": 2,
    "서먹서먹/XR": 2,
    "다/JX": 2,
    "공부/NNG": 1,
    "덜덜/MAG": 1,
    "떨/VV": 1,
    "으니까/EC": 1,
    "그만큼/MAG": 1,
    "의젓/XR": 1,
    "어야지/EF": 1,
    "목구멍/NNG": 1,
    "기어들/VV": 1,
    "가/VX": 3,
    "단가/EF": 3,
    "고니/NNG": 1,
    "설워서/NNG": 1,
    "ᆫ단다/EF": 1,
    "아하/IC": 3,
    "구나/EF": 1,
    "!/SF": 4,
    "서럽/VA-I": 2,
    "엄동설한/NNG": 1,
    "춥/VA-I": 3,
    "배고프/VA": 2,
    "제/XSN": 1,
    "ᆫ가/EF": 1,
    "허/XSV": 2,
    "자면/EC": 2,
    "여/EF": 1,
    "아부지/NNG": 5,
    "어떡허/VV": 1,
    "으까/EF": 1,
    "요러/VV": 2,
    "고/EF": 1,
    "턱/NNG": 1,
    "받치/VV": 1,
    "어리/VA": 2,
    "새치름히/MAG": 1,
    "건너다보/VV": 1,
    "마주치/VV": 1,
    "이제/NNG": 3,
    "습관/NNG": 1,
    "늘/MAG": 3,
    "끈적/XR": 1,
    "눈곱/NNG": 1,
    "무엇/NP": 1,
    "기쁘/VA": 1,
    "느이/NP": 1,
    "다행/NNG": 1,
    "밑구멍/NNG": 1,
    "득/NNG": 6,
    "여태/MAG": 1,
    "깊이/MAG": 1,
    "들여다보/VV": 1,
    "알콩달콩/MAG": 1,
    "개/NNG": 1,
    "대문/NNG": 2,
    "짖/VV": 1,
    "우아/XR": 1,
    "경건/XR": 1,
    "옷매무새/NNG": 1,
    "착착/MAG": 1,
    "가다듬/VV": 2,
    "부엌문/NNG": 2,
    "빠끔히/MAG": 1,
    "열/VV": 1,
    "확인/NNG": 1,
    "먼저/MAG": 1,
    "기척/NNG": 1,
    "나서/VV": 1,
    "어이/IC": 2,
    "영희/NNP": 4,
    "순희/NNP": 1,
    "마당/NNG": 1,
    "내려서/VV": 1,
    "위치/NNG": 1,
    "순/NNG": 1,
    "재/XPN": 1,
    "정렬/NNG": 1,
    "시키/XSV": 1,
    "참으로/MAG": 1,
    "엄숙/XR": 2,
    "어째/MAG": 2,
    "셋/NR": 3,
    "구나/EC": 2,
    "애/EF": 1,
    "가만/MAG": 1,
    "어라/EC": 3,
    "으음/IC": 1,
    "큰언니/NNG": 1,
    "동생/NNG": 2,
    "겄/EP": 1,
    "똑바로/MAG": 2,
    "자꾸/MAG": 5,
    "ᆯ라고/EC": 1,
    "쌓/VX": 1,
    "이놈/NP": 3,
    "야/JKV": 2,
    "몸가짐/NNG": 1,
    "혀/VV": 1,
    "넓/VA": 1,
    "광목/NNG": 1,
    "앞치마/NNG": 1,
    "무릎/NNG": 1,
    "꿇/VV": 1,
    "세우/VV": 1,
    "이마/NNG": 1,
    "만큼/JKB": 1,
    "경영/NNG": 1,
    "니/NP": 1,
    "우선/NNG": 1,
    "감사/NNG": 1,
    "일/NR": 1,
    "년/NNB": 1,
    "탈/NNG": 2,
    "크/VV": 1,
    "너희/NP": 4,
    "헌테/JKB": 1,
    "전하/VV": 1,
    "어허/IC": 1,
    "저놈/NP": 2,
    "뒤채/VV": 1,
    "네/EC": 1,
    "워째/MAG": 1,
    "모냥/NNG": 1,
    "스으을/NNP": 1,
    "야단/NNG": 1,
    "치/VV": 4,
    "생기/VV": 2,
    "혀/NNG": 1,
    "입천장/NNG": 1,
    "특유/NNG": 1,
    "입바람/NNG": 2,
    "잠들/VV": 2,
    "심심/XR": 1,
    "운전/NNG": 1,
    "방해/NNG": 1,
    "스으/NNG": 2,
    "돌아가/VV": 1,
    "전화벨/NNG": 2,
    "울리/VV": 2,
    "도대체/MAG": 3,
    "목소리/NNG": 3,
    "잔뜩/MAG": 2,
    "화/NNG": 3,
    "거/NP": 1,
    "당신/NP": 3,
    "ᆫ데/EF": 2,
    "여기/NP": 3,
    "파출소/NNG": 6,
    "주소/NNG": 4,
    "으니/EC": 4,
    "뭐/IC": 4,
    "채/MAG": 2,
    "끊기/VV": 2,
    "밤중/NNG": 1,
    "어서/EF": 1,
    "아뭇소리/NNG": 1,
    "말/VV": 2,
    "가르치/VV": 1,
    "어야지/EC": 2,
    "다짐/NNG": 1,
    "금방/MAG": 1,
    "냐믄/EC": 1,
    "여보세요/IC": 1,
    "아주머니/NNG": 3,
    "조경희/NNP": 6,
    "씨/NNB": 4,
    "습니까/EF": 1,
    "는데요/EF": 1,
    "그럼/MAJ": 2,
    "상/NNG": 4,
    "죠/EF": 4,
    "ᆫ데요/EF": 1,
    "거든요/EF": 1,
    "군요/EC": 1,
    "요새/NNG": 1,
    "퇴근/NNG": 1,
    "깜빡/MAG": 1,
    "잊/VV": 1,
    "종종/MAG": 1,
    "찾아오/VV": 1,
    "ᆸ니다/EC": 1,
    "구별/NNG": 1,
    "ᆸ니다요/EF": 1,
    "익스프레스/NNP": 2,
    "양반/NNG": 1,
    "지금/MAG": 2,
    "어딨/VA": 1,
    "나요/EF": 1,
    "끊/VV": 2,
    "요/JX": 1,
    "단단히/MAG": 1,
    "모양/NNG": 1,
    "에요/EF": 1,
    "어찌/MAG": 4,
    "든/EC": 2,
    "분명/MAG": 1,
    "지요/EF": 1,
    "다니까요/EF": 1,
    "서두르/VV": 1,
    "무심코/MAG": 1,
    "내던지/VV": 1,
    "'/SSO": 3,
    "야마/NNG": 1,
    "'/SSC": 3,
    "돌/VV": 1,
    "나머지/NNG": 2,
    "순경/NNG": 2,
    "푸르/VA-I": 1,
    "양/MM": 1,
    "볼/NNG": 1,
    "부어오르/VV": 1,
    "발길/NNG": 1,
    "내치/VV": 1,
    "통화/NNG": 1,
    "일단/MAG": 2,
    "안심/NNG": 1,
    "차/VA": 2,
    "바람/NNG": 3,
    "불/VV": 1,
    "밤길/NNP": 1,
    "위/NNG": 1,
    "정처/NNG": 1,
    "걷/VV-I": 2,
    "거나/EC": 3,
    "주저앉/VV": 1,
    "고도/EC": 1,
    "환히/MAG": 1,
    "보이/VV": 3,
    "얘/NP": 3,
    "ᆫ댄다/EF": 1,
    "일제히/MAG": 1,
    "돌아보/VV": 1,
    "잠옷/NNG": 3,
    "갈아입/VV-R": 1,
    "도로/MAG": 1,
    "벗/VV-R": 2,
    "사춘기/NNG": 1,
    "이라고/JKQ": 1,
    "귓불/NNG": 1,
    "붉어지/VV": 1,
    "이유/NNG": 3,
    "경험/NNG": 1,
    "으니까/EF": 1,
    "중학/NNG": 1,
    "생/XSN": 2,
    "야/JX": 2,
    "떠돌/VV": 1,
    "그제야/MAG": 2,
    "정착/NNG": 1,
    "셈/NNB": 3,
    "생리대/NNG": 3,
    "처리/NNG": 2,
    "문제/NNG": 3,
    "물론/MAG": 5,
    "빨/VV": 2,
    "삶/VV": 2,
    "햇볕/NNG": 2,
    "널/VV": 3,
    "마르/VV": 1,
    "다리미/NNG": 1,
    "다리/VV": 1,
    "착용/NNG": 1,
    "과정/NNG": 3,
    "그리도/MAG": 1,
    "귀찮/VA": 1,
    "던지/EC": 1,
    "생리/NNG": 5,
    "요/EC": 1,
    "표시/NNG": 1,
    "고는/EC": 2,
    "군데/NNB": 2,
    "세탁/NNG": 1,
    "거즈/NNG": 5,
    "굴러다니/VV": 1,
    "이불/NNG": 1,
    "묻히/VV": 1,
    "예사/NNG": 1,
    "건/EC": 2,
    "신경질/NNG": 2,
    "바락바락/MAG": 1,
    "칠칠/XR": 1,
    "딸내미/NNG": 1,
    "등짝/NNG": 2,
    "맵/VA-I": 1,
    "후려치/VV": 1,
    "퐁/NNP": 1,
    "지경/NNB": 1,
    "손수건/NNG": 1,
    "면/NNG": 1,
    "매번/MAG": 1,
    "말리/VV": 1,
    "쓰/VV": 5,
    "처박/VV": 1,
    "두/VX": 3,
    "욕/NNG": 1,
    "얻어맞/VV": 1,
    "방치/NNG": 1,
    "예사로/MAG": 1,
    "달/NNB": 2,
    "비상/NNG": 1,
    "어느/MM": 1,
    "무렵/NNB": 1,
    "밭일/NNG": 1,
    "혼잣소리/NNG": 1,
    "분명히/MAG": 1,
    "구시렁거리/VV": 1,
    "밤이슬/NNG": 1,
    "도록/EC": 1,
    "빨래/NNG": 2,
    "느냐는/ETM": 1,
    "타박/NNG": 1,
    "란/ETM": 3,
    "깨닫/VV-I": 1,
    "이미/MAG": 2,
    "부엌/NNG": 1,
    "짓/VV-I": 2,
    "아궁이/NNG": 1,
    "불/NNG": 1,
    "때/VV": 1,
    "쇠죽/NNG": 1,
    "끓이/VV": 2,
    "작두/NNG": 1,
    "짚/NNG": 1,
    "써/VV": 1,
    "그날/NNG": 2,
    "치욕/NNG": 1,
    "스럽/XSA-I": 4,
    "아무리/MAG": 1,
    "두고두고/MAG": 1,
    "입술/NNG": 2,
    "깨물/VV": 3,
    "혈흔/NNG": 1,
    "제대로/MAG": 1,
    "지우/VV": 1,
    "흔들/VV": 1,
    "멘스가/NNG": 1,
    "부끄런/NNG": 1,
    "다른/MM": 1,
    "에다/JKB": 1,
    "더냐고/EC": 1,
    "그때/NNG": 2,
    "만약/NNG": 1,
    "더라면/EC": 2,
    "그토록/MAG": 1,
    "이나/JX": 3,
    "초경/NNG": 1,
    "기/XSN": 1,
    "요즘/NNG": 2,
    "대놓고/MAG": 1,
    "축하/NNG": 1,
    "더라도/EC": 1,
    "적어도/MAG": 1,
    "멘스/NNG": 1,
    "부끄러/NNP": 1,
    "한마디/NNG": 1,
    "못내/MAG": 1,
    "아쉽/VA-I": 1,
    "불경/NNG": 1,
    "망측/XR": 1,
    "냐는/ETM": 1,
    "고개/NNG": 1,
    "외로/MAG": 1,
    "돌리/VV": 1,
    "정말로/MAG": 1,
    "완전/NNG": 1,
    "쫓아내/VV": 1,
    "이루어지/VV": 1,
    "불순분자/NNG": 1,
    "속삭이/VV": 1,
    "근데/MAJ": 1,
    "청바지/NNG": 1,
    "입/VV-R": 1,
    "잖아/EF": 4,
    "성장/NNG": 2,
    "지켜보/VV": 1,
    "힘/NNG": 2,
    "그래서/MAJ": 2,
    "무섭/VA-I": 1,
    "작/VA": 1,
    "곁/NNG": 1,
    "슬슬/MAG": 1,
    "다가오/VV": 1,
    "잠자/VV": 1,
    "땟국물/NNG": 1,
    "묻/VV-R": 1,
    "싫어하/VV": 1,
    "으라고/EC": 1,
    "백날/NNG": 1,
    "도통/MAG": 1,
    "들어먹/VV": 1,
    "목욕탕/NNG": 1,
    "강제/NNG": 1,
    "끌/VV": 2,
    "씻기/VV": 3,
    "ᆯ라치면/EC": 1,
    "어이/NNG": 1,
    "헛/XPN": 1,
    "웃음/NNG": 1,
    "깨끗/XR": 1,
    "이쁘/VA": 2,
    "좋아하/VV": 5,
    "야/EC": 6,
    "맨날/MAG": 1,
    "궁둥이/NNG": 1,
    "탁/MAG": 2,
    "내보내/VV": 1,
    "인물/NNG": 2,
    "훤하/VA": 2,
    "절로/MAG": 1,
    "벌어지/VV": 1,
    "한때/NNG": 2,
    "고추/NNG": 1,
    "만지/VV": 2,
    "커지/VV": 2,
    "그쪽/NP": 1,
    "몰리/VV": 2,
    "부분/NNG": 2,
    "고무줄/NNG": 1,
    "친친/MAG": 1,
    "동여매/VV": 1,
    "녀석/NNB": 2,
    "밀착/NNG": 1,
    "밖에/JX": 2,
    "조건/NNG": 1,
    "서운/XR": 1,
    "빗기/VV": 1,
    "작은애/NNG": 1,
    "업/VV-R": 1,
    "조석/NNG": 1,
    "대신/NNG": 1,
    "재우/VV": 1,
    "절대로/MAG": 1,
    "공허/XR": 1,
    "불행/NNG": 1,
    "충일/NNG": 1,
    "감/XSN": 1,
    "전적/NNG": 1,
    "투신/NNG": 1,
    "눈치/NNG": 1,
    "순전히/MAG": 1,
    "의지/NNG": 1,
    "만족/NNG": 1,
    "‘/SSO": 3,
    "원/NNG": 2,
    "’/SSC": 3,
    "완전히/MAG": 1,
    "체제/NNG": 1,
    "결코/MAG": 1,
    "아내/NNG": 1,
    "빼앗기/VV": 2,
    "꽉/MAG": 1,
    "틈/NNG": 1,
    "워낙/MAG": 1,
    "무심/NNG": 1,
    "언쟁/NNG": 1,
    "유병/NNG": 3,
    "숙/NNG": 3,
    "작업/NNG": 1,
    "도구/NNG": 1,
    "사진기/NNG": 1,
    "달랑/MAG": 1,
    "소위/MAG": 1,
    "작업실/NNG": 2,
    "돌입/NNG": 1,
    "기약/NNG": 1,
    "별거/NNG": 1,
    "상태/NNG": 1,
    "얼떨떨/XR": 1,
    "인지/NNG": 1,
    "즈음/NNB": 1,
    "윗집/NNG": 1,
    "서로/MAG": 1,
    "꼴/NNG": 1,
    "불쌍/XR": 2,
    "정확/NNG": 1,
    "확실/XR": 3,
    "저지르/VV": 1,
    "논/NNG": 1,
    "배/VV": 1,
    "멀뚱/XR": 1,
    "저렇/VA-I": 1,
    "기억/NNG": 2,
    "닭/NNG": 1,
    "잡아먹/VV": 1,
    "오리발/NNG": 1,
    "내밀/VV": 1,
    "격/NNB": 1,
    "씨/NNG": 3,
    "불과/MAG": 1,
    "결국/NNG": 1,
    "끔찍하/VA": 1,
    "핏줄/NNG": 1,
    "대하/VV": 1,
    "집착/NNG": 1,
    "씨앗/NNG": 1,
    "퍼뜨리/VV": 2,
    "종자/NNG": 1,
    "원래/NNG": 3,
    "거두/VV": 3,
    "몫/NNG": 1,
    "처녀/NNG": 1,
    "딸리/VV": 2,
    "홀아비/NNG": 3,
    "그런대로/MAG": 1,
    "과부/NNG": 1,
    "총각/NNG": 1,
    "시집가/VV": 1,
    "미혼모/NNG": 1,
    "미혼/NNG": 1,
    "부/NNG": 1,
    "무지르/VV": 1,
    "라구/EF": 1,
    "주체/NNG": 1,
    "어서라도/EC": 1,
    "뿌리/VV": 4,
    "직성/NNG": 1,
    "풀리/VV": 2,
    "땅/NNG": 1,
    "그곳/NP": 1,
    "불모지/NNG": 1,
    "비/NNG": 1,
    "옥/NNG": 1,
    "지/NNG": 1,
    "마구/MAG": 1,
    "밭/NNG": 1,
    "이분법/NNG": 1,
    "공식/NNG": 1,
    "지겹/VA-I": 1,
    "남성/NNG": 2,
    "공존/NNG": 2,
    "무시/NNG": 1,
    "아냐/IC": 1,
    "옆집/NNG": 1,
    "홀애비/NNG": 1,
    "원/IC": 1,
    "썅/NNP": 1,
    "얼마/NNG": 1,
    "결혼/NNG": 1,
    "답/XSA-I": 1,
    "선택/NNG": 1,
    "선물/NNG": 1,
    "라며/EC": 1,
    "수수깡/NNG": 5,
    "인형/NNG": 5,
    "둥지/NNG": 3,
    "지저분/XR": 1,
    "보따리/NNG": 2,
    "드디어/MAG": 1,
    "제법/MAG": 1,
    "독하/VA": 1,
    "냐고/EC": 1,
    "의심/NNG": 1,
    "차/VV": 1,
    "태도/NNG": 1,
    "이해/NNG": 1,
    "누그러뜨리/VV": 1,
    "만/NNB": 1,
    "지치/VV": 1,
    "역력히/MAG": 1,
    "드러내/VV": 1,
    "때로/MAG": 1,
    "적의/NNG": 1,
    "둔갑/NNG": 1,
    "울/VV": 1,
    "우/NNP": 1,
    "짜증/NNG": 3,
    "만류/NNG": 1,
    "신경전/NNG": 2,
    "작업대/NNG": 1,
    "내리치/VV": 1,
    "논문/NNG": 2,
    "심사/NNG": 1,
    "전시회/NNG": 1,
    "맞물리/VV": 1,
    "놓/VV": 1,
    "벌이/VV": 1,
    "느냐고/EC": 1,
    "더라구요/EF": 1,
    "으니까요/EF": 2,
    "한순간/NNG": 1,
    "외/NNB": 2,
    "무/XPN": 1,
    "관심/NNG": 1,
    "혼자/MAG": 1,
    "가늠/NNG": 1,
    "주절거리/VV": 1,
    "뒤꽁무니/NNG": 1,
    "빼/VV": 1,
    "으며/EC": 1,
    "근황/NNG": 1,
    "복/NNG": 1,
    "래/EF": 1,
    "침묵/NNG": 3,
    "어색/XR": 1,
    "불쑥/MAG": 1,
    "확정/NNG": 1,
    "장사/NNG": 1,
    "점포/NNG": 1,
    "전임/NNG": 2,
    "훌륭/XR": 1,
    "구만/EF": 1,
    "발광/NNG": 1,
    "같이/JKB": 1,
    "취직/NNG": 1,
    "감지덕지/MAG": 1,
    "뿐/JX": 1,
    "대학/NNG": 1,
    "쓰/VA": 2,
    "입맛/NNG": 2,
    "다시/VV": 2,
    "랴/EC": 2,
    "강사/NNG": 1,
    "알아보/VV": 1,
    "정신없/VA": 1,
    "덜/MAG": 1,
    "눈물겹/VA-I": 1,
    "은데/EC": 1,
    "인생/NNG": 1,
    "씹/VV-R": 1,
    "고/JKQ": 1,
    "분노/NNG": 1,
    "치밀/VV": 1,
    "째/XSN": 1,
    "깨/VV": 1,
    "깨우/VV": 3,
    "뭘/IC": 1,
    "저절로/MAG": 1,
    "장난감/NNG": 1,
    "이랑/JC": 1,
    "신기하/VA": 1,
    "배반/NNG": 2,
    "벌떡/MAG": 1,
    "일어나/VV": 2,
    "뜨/VV": 2,
    "안면/NNG": 1,
    "근육/NNG": 1,
    "씰룩거리/VV": 1,
    "한참/NNG": 1,
    "자/VV": 2,
    "접착/NNG": 1,
    "나가/VX": 1,
    "너덜너덜/MAG": 1,
    "집/VV-R": 1,
    "들/VX": 1,
    "이것/NP": 3,
    "망가지/VV": 1,
    "춤/NNG": 1,
    "추/VV": 1,
    "그네/NNG": 3,
    "생쥐/NNG": 6,
    "요것/NP": 1,
    "침대/NNG": 1,
    "고물고물/MAG": 1,
    "기어나오/VV": 1,
    "애기/NNG": 1,
    "기겁/NNG": 1,
    "실망/NNG": 1,
    "열/NNG": 1,
    "반응/NNG": 1,
    "신통/NNG": 1,
    "또다시/MAG": 1,
    "자라/VV": 1,
    "날로/MAG": 1,
    "작아지/VV": 1,
    "소파/NNG": 2,
    "우두커니/MAG": 1,
    "이번/NNG": 1,
    "연극/NNG": 2,
    "재밌/VA": 2,
    "위하/VV": 1,
    "특별히/MAG": 1,
    "만들/VX": 1,
    "어린애/NNG": 1,
    "세요/EF": 1,
    "유치원/NNG": 1,
    "갖/VV": 1,
    "라구요/EF": 1,
    "새집/NNG": 1,
    "아니/MAG": 1,
    "필요/NNG": 1,
    "끝/NNG": 1,
    "맺/VV": 1,
    "기에/EC": 1,
    "라든가/EC": 1,
    "야단맞/VV": 1,
    "존댓말/NNG": 1,
    "리/NNB": 1,
    "야단치/VV": 1,
    "그만두/VV": 2,
    "고함/NNG": 1,
    "다니/EC": 1,
    "이렇/VA-I": 1,
    "바/NNB": 1,
    "를/JX": 1,
    "든지/EC": 1,
    "서/JKS": 1,
    "구석/NNG": 2,
    "훑/VV": 1,
    "현관문/NNG": 1,
    "박차/VV": 1,
    "아파트/NNG": 3,
    "광장/NNG": 3,
    "홀로/MAG": 1,
    "엉거주춤/MAG": 1,
    "실루엣/NNG": 1,
    "붙잡/VV-R": 1,
    "틀림없이/MAG": 1,
    "어떡하/VV": 1,
    "곰곰이/MAG": 1,
    "겨울바람/NNG": 1,
    "휘돌/VV": 1,
    "얇/VA": 1,
    "바짓단/NNG": 2,
    "뒤흔들/VV": 1,
    "깃발/NNG": 1,
    "펄럭거리/VV": 1,
    "불어오/VV": 1,
    "훅/MAG": 1,
    "들이마시/VV": 1,
    "사내/NNG": 1,
    "담배꽁초/NNG": 1,
    "휙/MAG": 1,
    "던지/VV": 1,
    "뚜벅뚜벅/MAG": 1,
    "멀/VA": 1,
    "악/NNG": 1,
    "뒤돌아보/VV": 1,
    "휭/MAG": 1,
    "줄기/NNG": 1,
    "한/XPN": 1,
    "가운데/NNG": 1,
    "뚫/VV": 1,
    "지나가/VV": 1,
    "들이/VV": 1,
    "으리라/EF": 1,
    "승강기/NNG": 1,
    "올라오/VV": 1,
    "결심/NNG": 1,
    "굳히/VV": 2,
    "현관/NNG": 1,
    "안/NNG": 1,
    "이야말로/JX": 1,
    "화장실/NNG": 1,
    "맥/NNG": 1,
    "재빨리/MAG": 1,
    "한숨/NNG": 1,
    "몰아쉬/VV": 1,
    "시계/NNG": 1,
    "다음/NNG": 1,
    "리모컨/NNG": 1,
    "누르/VV": 1,
    "시간대/NNG": 1,
    "누리/VV": 1,
    "일상/NNG": 2,
    "끼이/VV": 1,
    "그림자/NNG": 1,
    "벽/NNG": 1,
    "일리야/NNP": 1,
    "레삔/NNP": 1,
    "그림/NNG": 2,
    "낮/VA": 1,
    "읊조리/VV": 1,
    "일쑤/NNG": 1,
    "모두/MAG": 1,
    "온몸/NNG": 1,
    "소름/NNG": 1,
    "오소소/NNG": 1,
    "돋/VV-R": 1,
    "내버리/VV": 1,
    "화면/NNG": 1
  }
}